Workbook

Sheet Data_Vintage
A1: Мэдээллийн он сар (Data vintage) — тайлант үе 2026-07
A2: Which month each source actually carries. CURRENT = the reported month. LAGGED = the source has not published the reported month yet, so the PREVIOUS month's figure is shown and the period column says which. Nothing is ever extrapolated or carried forward silently.
A4: Эх сурвалж (Source) | B4: Хаана орсон (Feeds) | C4: Аль сарынх (Period of the data) | D4: Төлөв (Status) | E4: Тайлбар (Note)
A5: Customs (gaali.mn) | B5: Trade, Commodities, Border prices, Trade_Sections | C5: 2026-07 | D5: CURRENT | E5: monthly bulletin for the reported month
A6: NSO national accounts | B6: GDP_Growth, GDP_Sectors | C6: 2026-Q2 | D6: QUARTERLY | E6: quarterly series — the latest quarter ending on or before the reported month
A7: Эдийн засгийн сарын өсөлт (NSO monthly GDP growth) | B7: GDP_Growth — monthly growth and sector contributions | C7: 2026-05 | D7: LAGGED | E7: WARNING: MIEG newest period is 2026-05, target is 2026-07
A8: Mongolbank bulletin | B8: Inflation, policy rate, budget, FX | C8: 2026-07 | D8: CURRENT | E8: issue mongolbank_bulletin.xlsx
A9: Bank balance sheet | B9: Banking (assets, loans, NPL, equity) | C9: 2026-07 | D9: CURRENT | E9: latest column in the report: 2026.07.31
A10: Deposit tree | B10: Banking (харилцах, хадгаламж) | C10: 2026-07 | D10: CURRENT | E10: source: deposits_export.json, 19 period column(s)
A11: Bank loan report | B11: Loan_Detail (bridge, sectors, NPL, rates) | C11: 2026-07 | D11: CURRENT | E11: monthly flow statement
A12: Balance of payments | B12: External_Sector (BoP detail) | C12: 2026-06 | D12: LAGGED | E12: BoP export reaches month 6 only; these are cumulative I-6 figures, not I-7.
A13: NSO Худалдааны салбарын нийт б | B13: Real_Sector — trade | C13: 2026-06 | D13: LAGGED | E13: M, 5 components
A14: NSO Зочид буудлын салбарын орл | B14: Real_Sector — hotel | C14: 2026-06 | D14: LAGGED | E14: M, 5 components
A15: NSO Нийтийн хоолны салбарын ор | B15: Real_Sector — food | C15: 2026-06 | D15: LAGGED | E15: M, 5 components
... A20: Mongolbank cards | B20: External_Sector (reserves, FDI, debt) | C20: see card dates | D20: PER-CARD | E20: each card carries its own 'as of' date: 2026 оны 1-р улирал, 2026 оны 6-р сар, 2026 оны 7-р сар, 2026 оны 7-р сарын байдлаар
A22: АНХААР (read before using): Эдийн засгийн сарын өсөлт (NSO monthly GDP growth) is 2026-05, not 2026-07; Balance of payments is 2026-06, not 2026-07; NSO Худалдааны салбарын нийт б is 2026-06, not 2026-07; NSO Зочид буудлын салбарын орл is 2026-06, not 2026-07; NSO Нийтийн хоолны салбарын ор is 2026-06, not 2026-07

Sheet Summary
A1: Macroeconomic KPI Summary — 2026 оны 7-р сар
A2: Green figures are live links to the data sheets. Feeds deck slide 3 and headline text on slides 4, 6, 9, 12, 13.
A4: МЭДЭЭЛЛИЙН ОН САР / DATA AS OF: энэ хуудас олон эх сурвалжийг нэгтгэнэ (this sheet mixes sources). ӨМНӨХ САРЫНХ / previous month: Эдийн засгийн сарын өсөлт (NSO monthly GDP growth) = 2026-05; Balance of payments = 2026-06; NSO Худалдааны салбарын нийт б = 2026-06; NSO Зочид буудлын салбарын орл = 2026-06; NSO Нийтийн хоолны салбарын ор = 2026-06 — дэлгэрэнгүйг Data_Vintage хуудаснаас (see Data_Vintage)
A6: Үзүүлэлт (Indicator) | B6: Утга (Value) | C6: Нэгж (Unit) | D6: Period / note | E6: Source | F6: Deck slide
A7: Бодит ДНБ-ий өсөлт (Real GDP growth, YoY cum.) | B7: =GDP_Growth!C60 | C7: % | D7: 2026-Q2 | E7: NSO 1212.mn | F7: 3, 4
A8: Эдийн засгийн өсөлтийн сарын индикатор (MIEG, YoY cum.) | B8: 0.0732 | C8: % | D8: WARNING: MIEG newest period is 2026-05, target is 2026-07 | E8: NSO 1212.mn | F8: 4
A9: Инфляц (Inflation, headline) | B9: 0.13 | C9: % | D9: Mongolbank bulletin, 2026 оны 7-р сарын байдлаар | E9: MB bulletin | F9: 3, 6
A10: Инфляцын зорилтот түвшин (Inflation target) | B10: 0.08 | C10: % | D10: Mongolbank official target | E10: Mongolbank | F10: 6
A11: Бодлогын хүү (Policy rate) | B11: 0.12 | C11: % | D11: MB bulletin, Rate sheet | E11: Mongolbank | F11: 3, 8
A12: Зээлийн хүү (Bank loan rate, new loans) | B12: 0.174 | C12: % | D12: 2026 оны 7-р сар | E12: Mongolbank | F12: 8
A13: Хадгаламжийн хүү (Deposit rate, new deposits) | B13: 0.114 | C13: % | D13: 2026 оны 7-р сар | E13: Mongolbank | F13: 8
A14: Банкны салбарын зээл (Bank loans outstanding) | B14: 47.9 | C14: level | D14: tln MNT, 2026 оны 7-р сар | E14: Mongolbank | F14: 16
A15: Ипотекийн зээл (Mortgage loans outstanding) | B15: 12.4 | C15: level | D15: tln MNT, 2026 оны 7-р сар | E15: Mongolbank | F15: 16
A16: Нийт экспорт (Total export) | B16: =Trade!C7 | C16: level | D16: thous. USD, 2026 оны 7-р сарын байдлаар | E16: Customs gaali.mn | F16: 9
A17: Нийт импорт (Total import) | B17: =Trade!C8 | C17: level | D17: thous. USD, 2026 оны 7-р сарын байдлаар | E17: Customs gaali.mn | F17: 9
A18: Худалдааны тэнцэл (Trade balance) | B18: =Trade!C7-Trade!C8 | C18: level | D18: thous. USD; formula: export cell - import cell | E18: Customs gaali.mn | F18: 9
A19: Экспортын өсөлт (Export growth, YoY) | B19: =IFERROR(Trade!C7/Trade!B7-1,"") | C19: % | D19: formula: current / previous - 1 | E19: Customs gaali.mn | F19: 9
A20: Импортын өсөлт (Import growth, YoY) | B20: =IFERROR(Trade!C8/Trade!B8-1,"") | C20: % | D20: formula: current / previous - 1 | E20: Customs gaali.mn | F20: 9
A21: Худалдааны тэнцэл, өмнөх оны эсрэг (Trade balance vs prev yr) | B21: =IFERROR(Trade!C9/Trade!B9,"") | C21: x | D21: balance multiple | E21: Customs gaali.mn | F21: 9
A22: Нүүрсний экспортын хэмжээ (Coal export volume) | B22: =IFERROR(Commodities!D7/1E9,"") | C22: level | D22: mln t | E22: Customs gaali.mn | F22: 10, 13
A23: Нүүрсний хэмжээний өсөлт (Coal volume growth, YoY) | B23: =IFERROR(Commodities!D7/Commodities!C7-1,"") | C23: % | D23: formula over quantity cells | E23: Customs gaali.mn | F23: 10
A24: Зэсийн баяжмалын экспортын хэмжээ (Copper conc. export volume) | B24: =IFERROR(Commodities!D8/1E6,"") | C24: level | D24: thous. t | E24: Customs gaali.mn | F24: 10
A25: Зэсийн хэмжээний өсөлт (Copper volume growth, YoY) | B25: =IFERROR(Commodities!D8/Commodities!C8-1,"") | C25: % | D25: formula over quantity cells | E25: Customs gaali.mn | F25: 10
A26: Алтны экспортын хэмжээ (Gold export volume) | B26: =Commodities!D9 | C26: level | D26: kg | E26: Customs gaali.mn | F26: 10
A27: Алтны хэмжээний өсөлт (Gold volume growth, YoY) | B27: =IFERROR(Commodities!D9/Commodities!C9-1,"") | C27: % | D27: formula over quantity cells | E27: Customs gaali.mn | F27: 10
A28: Гадаад валютын нөөц (FX reserves) | B28: 7963 | C28: level | D28: mln USD, 2026 оны 7-р сар | E28: Mongolbank | F28: 3, 12
A29: Төлбөрийн тэнцэл (Balance of payments) | B29: 567 | C29: level | D29: mln USD, 2026 оны 6-р сар | E29: Mongolbank | F29: 12
A30: Нийт гадаад өр (External debt) | B30: 40218 | C30: level | D30: mln USD, 2026 оны 1-р улирал | E30: Mongolbank | F30: 12
A31: ШХО-ын үлдэгдэл (FDI stock) | B31: 37509 | C31: level | D31: mln USD, 2026 оны 1-р улирал | E31: Mongolbank | F31: 12
A32: Ам.долларын ханш (USD/MNT rate, eop) | B32: 3592.73 | C32: level | D32: YoY 0.1%, MB bulletin Exchange rate sheet | E32: MB bulletin | F32: 3
A33: Банкны нийт зээлийн өсөлт (DC loans growth, YoY) | B33: 0.13 | C33: % | D33: loans outstanding 48.19 tln ₮ | E33: MB bulletin | F33: 16
A34: Иргэдийн зээлийн өсөлт (Individuals' loans growth, YoY) | B34: 0.121 | C34: % | D34: individuals 26.65 tln ₮ | E34: MB bulletin | F34: 16
A35: Банкны нийт актив (Bank total assets) | B35: =IFERROR(Banking!C7/1E6,"") | C35: level | D35: tln MNT, as of 2026.07.31 | E35: Mongolbank | F35: 16
A36: Чанаргүй зээлийн өөрчлөлт (Bank NPL change since Jan) | B36: =IFERROR(Banking!C12/Banking!B12-1,"") | C36: % | D36: change measured 2025.07.31 -> 2026.07.31 (earliest column in the report; not necessarily 31 Dec) | E36: Mongolbank | F36: 16
A37: Төсвийн тэнцэл (Budget balance, cum.) | B37: -2206.4 | C37: level | D37: bln MNT, 2026 оны 7-р сарын байдлаар | E37: MB bulletin | F37: 13
A38: Төсвийн орлого, гүйцэтгэл (Budget revenue collected) | B38: 19829.8 | C38: level | D38: bln MNT | E38: MB bulletin | F38: 13

Sheet GDP_Growth
A1: Real GDP (2015 prices) — levels & growth
A2: Deck slide 4. Source datapoints: NSO National Accounts (DT_NSO_0500_004V1). All growth figures are formulas over the quarterly levels below.
A4: МЭДЭЭЛЛИЙН ОН САР / DATA AS OF: NSO national accounts — 2026-Q2 (QUARTERLY) [тайлант үе / reported month: 2026-07]
A6: Улирлын бодит ДНБ (Quarterly real GDP levels, mln MNT, 2015 prices)
A7: Он (Year) | B7: Улирал (Quarter) | C7: Бодит ДНБ (Real GDP, 2015p) | D7: Жилийн өсөлт (YoY growth)
A8: 2015 | B8: 1 | C8: 4193640.8
A9: 2015 | B9: 2 | C9: 6296039.6
A10: 2015 | B10: 3 | C10: 6303713.8
A11: 2015 | B11: 4 | C11: 6101386.7
A12: 2016 | B12: 1 | C12: 4302469.6 | D12: =IFERROR(C12/C8-1,"")
A13: 2016 | B13: 2 | C13: 6353504.7 | D13: =IFERROR(C13/C9-1,"")
A14: 2016 | B14: 3 | C14: 5990073.9 | D14: =IFERROR(C14/C10-1,"")
A15: 2016 | B15: 4 | C15: 6589815.6 | D15: =IFERROR(C15/C11-1,"")
A16: 2017 | B16: 1 | C16: 4550537.5 | D16: =IFERROR(C16/C12-1,"")
A17: 2017 | B17: 2 | C17: 6731828.3 | D17: =IFERROR(C17/C13-1,"")
A18: 2017 | B18: 3 | C18: 6388502.9 | D18: =IFERROR(C18/C14-1,"")
A19: 2017 | B19: 4 | C19: 6874772 | D19: =IFERROR(C19/C15-1,"")
A20: 2018 | B20: 1 | C20: 4836449.6 | D20: =IFERROR(C20/C16-1,"")
A21: 2018 | B21: 2 | C21: 7225676.3 | D21: =IFERROR(C21/C17-1,"")
A22: 2018 | B22: 3 | C22: 6841775.1 | D22: =IFERROR(C22/C18-1,"")
A23: 2018 | B23: 4 | C23: 7542770.3 | D23: =IFERROR(C23/C19-1,"")
... A53: 2026 | B53: 2 | C53: 9692115 | D53: =IFERROR(C53/C49-1,"")
A56: Өссөн дүнгээрх өсөлт (Cumulative growth by period = SUM of quarters vs same quarters a year earlier)
A57: Он (Year) | B57: I-III | C57: I-VI | D57: I-IX | E57: I-XII
A58: 2024 | B58: =IFERROR(SUM(C44:C44)/SUM(C40:C40)-1,"") | C58: =IFERROR(SUM(C44:C45)/SUM(C40:C41)-1,"") | D58: =IFERROR(SUM(C44:C46)/SUM(C40:C42)-1,"") | E58: =IFERROR(SUM(C44:C47)/SUM(C40:C43)-1,"")
A59: 2025 | B59: =IFERROR(SUM(C48:C48)/SUM(C44:C44)-1,"") | C59: =IFERROR(SUM(C48:C49)/SUM(C44:C45)-1,"") | D59: =IFERROR(SUM(C48:C50)/SUM(C44:C46)-1,"") | E59: =IFERROR(SUM(C48:C51)/SUM(C44:C47)-1,"")
A60: 2026 | B60: =IFERROR(SUM(C52:C52)/SUM(C48:C48)-1,"") | C60: =IFERROR(SUM(C52:C53)/SUM(C48:C49)-1,"")
A63: Эдийн засгийн өсөлтийн сарын индикатор (MIEG, cumulative YoY, NSO DT_NSO_0500_001V5)
A64: Сар (Month) | B64: Өсөлт (Growth, YoY cum.)
A65: 2016-01 | B65: 0.0274
A66: 2016-02 | B66: 0.0336
A67: 2016-03 | B67: 0.026
A68: 2016-04 | B68: 0.0256
A69: 2016-05 | B69: 0.0251
A70: 2016-06 | B70: 0.0158
A71: 2016-07 | B71: 0.0055
A72: 2016-08 | B72: 0.0004
A73: 2016-09 | B73: -0.0088
A74: 2016-10 | B74: 0.0001
A75: 2016-11 | B75: 0.0097
A76: 2016-12 | B76: 0.0149
... A189: 2026-05 | B189: 0.0732
A192: Салбаруудын хувь нэмэр (MIEG sector contributions, pp, 2026-05)
A193: Салбар (Sector) | B193: Хувь нэмэр (pp)
A194: Хөдөө аж ахуй | B194: 1.52
A195: Уул уурхай, олборлолт | B195: 3.71
A196: Аж үйлдвэр, барилга | B196: 0.27
A197: Үйлчилгээ | B197: 1.91
A198: Бүтээгдэхүүний цэвэр татвар | B198: -0.09
A199: Нийт (Total, pp) | B199: =SUM(B194:B198)

Sheet GDP_Sectors
A1: Sector contributions to real GDP growth (pp)
A2: Deck slide 5. Contribution = Δsector real value added / prior-period total GDP (computed upstream from NSO levels). Total row is a SUM formula and must equal GDP growth.
A4: МЭДЭЭЛЛИЙН ОН САР / DATA AS OF: NSO national accounts — 2026-Q2 (QUARTERLY) [тайлант үе / reported month: 2026-07]
A6: Салбар (Sector) | B6: 2025 (I-XII) | C6: 2026 (I-VI)
A7: Хөдөө аж ахуй, ойн аж ахуй, загас барилт, ан агнуур (Agriculture, forestry, fishing & hunting) | B7: 2.86 | C7: 1.45
A8: Уул уурхай, олборлолт (Mining & quarrying) | B8: 1.41 | C8: 3.91
A9: Боловсруулах үйлдвэрлэл (Manufacturing) | B9: 0.74 | C9: 0.07
A10: Цахилгаан, хий, уур, агааржуулалт (Electricity, gas, steam & air conditioning) | B10: 0.25 | C10: 0.23
A11: Барилга (Construction) | B11: 0.52 | C11: 0.16
A12: Бөөний болон жижиглэн худалдаа, машин, мотоциклийн засвар, үйлчилгээ (Wholesale & retail trade; vehicle repair) | B12: -0.55 | C12: -0.02
A13: Тээвэр ба агуулахын үйл ажиллагаа (Transportation & storage) | B13: 0.31 | C13: 0.82
A14: Мэдээлэл, холбоо (Information & communication) | B14: 0.24 | C14: 0.25
A15: Үйлчилгээний бусад үйл ажиллагаа (Other service activities) | B15: 1.03 | C15: 0.76
A16: Бүтээгдэхүүний цэвэр татвар (Net taxes on products) | B16: 0.04 | C16: 0.05
A17: Нийт (Total = GDP growth, pp) | B17: =SUM(B7:B16) | C17: =SUM(C7:C16)

Sheet Inflation
A1: Inflation
A2: Deck slides 6-7. Headline from the Mongolbank statistical bulletin; the 12-month CPI series requires the NSO CPI table id (see raw_ingestor.py NSO_TABLES). Values stored as fractions, shown as % via number format.
A4: МЭДЭЭЛЛИЙН ОН САР / DATA AS OF: Mongolbank bulletin — 2026-07 (CURRENT) [тайлант үе / reported month: 2026-07]
A6: Үзүүлэлт (Indicator) | B6: Утга (Value) | C6: Note
A7: Инфляц (Headline inflation, YoY) | B7: 0.13 | C7: Mongolbank bulletin (mongolbank_bulletin.xlsx, period 2026-07)
A8: Монголбанкны зорилт (Mongolbank target) | B8: 0.08 | C8: official target
A9: Зорилтоос зөрүү (Gap vs target) | B9: =B7-B8 | C9: formula: headline - target; positive = above target
A10: Махны хувь нэмэр (Meat contribution) | B10: n/a | C10: pp of headline, when stated in the source
A11: Бодлогын хүү (Policy rate) | B11: 0.12 | C11: MB bulletin, Rate sheet
A12: Махны үнийн өсөлт (Meat price growth, YoY) | C12: MANUAL entry (slide 7) -- CPI PDF automation dropped by design; type the value from the NSO CPI presentation here
A13: Шатахууны үнийн өсөлт (Fuel price growth, YoY) | C13: MANUAL entry (slide 7) -- CPI PDF automation dropped by design; type the value from the NSO CPI presentation here
A16: Сарын цуваа (Monthly series, Mongolbank bulletin) — slides 6 & 8
A17: Сар (Month) | B17: Инфляц, улс (CPI YoY, national) | C17: Инфляц, УБ (CPI YoY, UB) | D17: Зорилт (Target) | E17: Бодлогын хүү (Policy rate) | F17: Хадгаламжийн хүү (Deposit rate, new MNT) | G17: Шинэ зээлийн хүү, зах зээлийн (New loan rate, market) | H17: Шинэ зээлийн хүү, хөтөлбөрийн зээл оруулснаар (incl. subsidised) | I17: Зөрүү (Gap, pp) | J17: Ам.долларын ханш (USD/MNT, eop)
A18: 2025-04 | B18: 0.087 | C18: 0.099 | D18: 0.08 | E18: 0.12 | F18: 0.1199 | G18: 0.172 | H18: 0.1662 | I18: =IFERROR((G18-H18)*100,"") | J18: 3570.82
A19: 2025-05 | B19: 0.083 | C19: 0.094 | D19: 0.08 | E19: 0.12 | F19: 0.1188 | G19: 0.1718 | H19: 0.1656 | I19: =IFERROR((G19-H19)*100,"") | J19: 3573.95
A20: 2025-06 | B20: 0.082 | C20: 0.094 | D20: 0.08 | E20: 0.12 | F20: 0.1159 | G20: 0.1727 | H20: 0.1681 | I20: =IFERROR((G20-H20)*100,"") | J20: 3580.94
A21: 2025-07 | B21: 0.081 | C21: 0.093 | D21: 0.08 | E21: 0.12 | F21: 0.114 | G21: 0.171 | H21: 0.1687 | I21: =IFERROR((G21-H21)*100,"") | J21: 3587.49
A22: 2025-08 | B22: 0.088 | C22: 0.098 | D22: 0.08 | E22: 0.12 | F22: 0.1172 | G22: 0.1703 | H22: 0.168 | I22: =IFERROR((G22-H22)*100,"") | J22: 3592.79
A23: 2025-09 | B23: 0.09 | C23: 0.099 | D23: 0.08 | E23: 0.12 | F23: 0.1187 | G23: 0.1726 | H23: 0.1692 | I23: =IFERROR((G23-H23)*100,"") | J23: 3592.78
A24: 2025-10 | B24: 0.092 | C24: 0.099 | D24: 0.08 | E24: 0.12 | F24: 0.1228 | G24: 0.1736 | H24: 0.1697 | I24: =IFERROR((G24-H24)*100,"") | J24: 3585.29
A25: 2025-11 | B25: 0.082 | C25: 0.087 | D25: 0.08 | E25: 0.12 | F25: 0.117 | G25: 0.1734 | H25: 0.1697 | I25: =IFERROR((G25-H25)*100,"") | J25: 3553.58
A26: 2025-12 | B26: 0.075 | C26: 0.076 | D26: 0.08 | E26: 0.12 | F26: 0.1203 | G26: 0.1727 | H26: 0.1674 | I26: =IFERROR((G26-H26)*100,"") | J26: 3556.81
A27: 2026-01 | B27: 0.075 | C27: 0.075 | D27: 0.08 | E27: 0.12 | F27: 0.1174 | G27: 0.1713 | H27: 0.1698 | I27: =IFERROR((G27-H27)*100,"") | J27: 3564.08
A28: 2026-02 | B28: 0.065 | C28: 0.06 | D28: 0.08 | E28: 0.12 | F28: 0.1184 | G28: 0.1726 | H28: 0.1709 | I28: =IFERROR((G28-H28)*100,"") | J28: 3565.55
A29: 2026-03 | B29: 0.074 | C29: 0.073 | D29: 0.08 | E29: 0.12 | F29: 0.1184 | G29: 0.1759 | H29: 0.1737 | I29: =IFERROR((G29-H29)*100,"") | J29: 3568.71
... A33: 2026-07 | B33: 0.13 | C33: 0.13 | D33: 0.08 | E33: 0.12 | F33: 0.1144 | G33: 0.1741 | H33: 0.1723 | I33: =IFERROR((G33-H33)*100,"") | J33: 3592.73
A36: Инфляцад нөлөөлж буй бүлгүүд (CPI component contributions to headline, 2026-07)
A37: Бүлэг (Category) | B37: Хувь нэмэр, 2026-07 (pp) | C37: Эзлэх хувь, 2026-07 (share) | D37: Хувь нэмэр, 2025-07 (pp) | E37: Эзлэх хувь, 2025-07 (share) | F37: Бүлгийн өсөлт (Category YoY) | G37: Индекс (Level)
A38: Хүнсний бараа, согтууруулах бус ундаа Food & non-alcoholic beverages | B38: 7.01 | C38: 0.53716475 | D38: 1.8 | E38: 0.22222222 | F38: 0.255 | G38: 39.46
A39: Тээвэр Transports | B39: 1.48 | C39: 0.11340996 | D39: 0.44 | E39: 0.054320988 | F39: 0.1 | G39: 18.63
A40: Хувцас, бөс бараа, гутал Clothing, footwear and cloths | B40: 0.93 | C40: 0.071264368 | D40: 1.17 | E40: 0.14444444 | F40: 0.072 | G40: 15.86
A41: Боловсролын үйлчилгээ Education | B41: 0.76 | C41: 0.058237548 | D41: 1 | E41: 0.12345679 | F41: 0.128 | G41: 7.72
A42: Бусад бараа үйлчилгээ Miscellaneous goods & services | B42: 0.58 | C42: 0.044444444 | D42: 0.59 | E42: 0.072839506 | F42: 0.098 | G42: 7.51
A43: Орон сууц, ус, түлш, цахилгаан Housing, water, electricity, and fuels | B43: 0.54 | C43: 0.04137931 | D43: 1.89 | E43: 0.23333333 | F43: 0.051 | G43: 12.7
A44: Эм, тариа, эмнэлгийн үйлчилгээ Medical care & services | B44: 0.53 | C44: 0.040613027 | D44: 0.38 | E44: 0.04691358 | F44: 0.076 | G44: 8.6
A45: Зочид буудал, нийтийн хоол, дотуур байр Restraurants hotels | B45: 0.43 | C45: 0.032950192 | D45: 0.3 | E45: 0.037037037 | F45: 0.162 | G45: 3.49
A46: Гэр ахуйн тавилга, гэр ахуйн бараа Furnishings, household equipment & tools | B46: 0.41 | C46: 0.031417625 | D46: 0.3 | E46: 0.037037037 | F46: 0.087 | G46: 5.87
A47: Согтууруу- лах ундаа, тамхи Alcoholic beverages, tobacco | B47: 0.12 | C47: 0.0091954023 | D47: 0.04 | E47: 0.0049382716 | F47: 0.126 | G47: 1.23
A48: Амралт, чөлөөт цаг, соёлын бараа үйлчилгээ Recreation & culture | B48: 0.1 | C48: 0.0076628352 | D48: 0.09 | E48: 0.011111111 | F48: 0.066 | G48: 1.82
A49: Холбооны хэрэгсэл, шуудангийн үйлчилгээ Communi- cation | B49: 0.08 | C49: 0.0061302682 | D49: 0.04 | E49: 0.0049382716 | F49: 0.016 | G49: 6.03
A50: Даатгал санхүүгийн үйлчилгээ Insurance and financial services | B50: 0.08 | C50: 0.0061302682 | D50: 0.06 | E50: 0.0074074074 | F50: 0.17 | G50: 0.6
A51: Улсын инфляц (Total, pp — must match headline) | B51: =SUM(B38:B50) | C51: =SUM(C38:C50) | D51: =SUM(D38:D50) | E51: =SUM(E38:E50)

Sheet Trade
A1: Foreign trade
A2: Deck slide 9. Source: Customs gaali.mn monthly bulletin, sheet 1. Money: thousand USD unless noted. YoY/balance columns are formulas.
A4: МЭДЭЭЛЛИЙН ОН САР / DATA AS OF: Customs (gaali.mn) — 2026-07 (CURRENT) [тайлант үе / reported month: 2026-07]
A6: Үзүүлэлт (Indicator) | B6: Өмнөх он (Prev year, cum.) | C6: Тайлант он (Current year, cum.) | D6: Өсөлт (YoY) | E6: сая $ (mln USD, cur.)
A7: Экспорт (Export) | B7: 7751535.2 | C7: 12205932 | D7: =IFERROR(C7/B7-1,"") | E7: =IFERROR(C7/1000,"")
A8: Импорт (Import) | B8: 6480784.2 | C8: 7158063.4 | D8: =IFERROR(C8/B8-1,"") | E8: =IFERROR(C8/1000,"")
A9: Худалдааны тэнцэл (Trade balance) | B9: =B7-B8 | C9: =C7-C8 | D9: =IFERROR(C9/B9,"") | E9: =IFERROR(C9/1000,"")
A12: Сар бүрийн өссөн худалдаа (Monthly cumulative trade, mln USD) — grows as monthly workbooks are cached
A13: Он (Year) | B13: Сар (Month) | C13: Экспорт, өссөн (Export cum., mln $) | D13: Импорт, өссөн (Import cum., mln $) | E13: Тэнцэл (Balance, mln $) | F13: Экспортын өсөлт (Export YoY) | G13: Импортын өсөлт (Import YoY) | H13: Нийт эргэлт (Turnover, mln $) | I13: Эргэлтийн өсөлт (Turnover YoY)
A14: 2024 | B14: 1 | C14: 1324.925 | D14: 935.9896 | E14: =C14-D14 | H14: =C14+D14
A15: 2024 | B15: 2 | C15: 2240.2788 | D15: 1595.8787 | E15: =C15-D15 | H15: =C15+D15
A16: 2024 | B16: 3 | C16: 3658.8553 | D16: 2414.2793 | E16: =C16-D16 | H16: =C16+D16
A17: 2024 | B17: 4 | C17: 4937.0968 | D17: 3426.2195 | E17: =C17-D17 | H17: =C17+D17
A18: 2024 | B18: 5 | C18: 6355.9796 | D18: 4395.1571 | E18: =C18-D18 | H18: =C18+D18
A19: 2024 | B19: 6 | C19: 7886.2146 | D19: 5378.4283 | E19: =C19-D19 | H19: =C19+D19
A20: 2024 | B20: 7 | C20: 9265.8501 | D20: 6411.1281 | E20: =C20-D20 | H20: =C20+D20
A21: 2024 | B21: 8 | C21: 10625.089 | D21: 7501.6131 | E21: =C21-D21 | H21: =C21+D21
A22: 2024 | B22: 9 | C22: 11782.653 | D22: 8608.2879 | E22: =C22-D22 | H22: =C22+D22
A23: 2024 | B23: 10 | C23: 13207.173 | D23: 9579.7805 | E23: =C23-D23 | H23: =C23+D23
A24: 2024 | B24: 11 | C24: 14596.419 | D24: 10567.099 | E24: =C24-D24 | H24: =C24+D24
A25: 2025 | B25: 1 | C25: 1019.1869 | D25: 973.1577 | E25: =C25-D25 | F25: =IFERROR(C25/C14-1,"") | G25: =IFERROR(D25/D14-1,"") | H25: =C25+D25 | I25: =IFERROR(H25/H14-1,"")
A26: 2025 | B26: 2 | C26: 2004.9174 | D26: 1710.8877 | E26: =C26-D26 | F26: =IFERROR(C26/C15-1,"") | G26: =IFERROR(D26/D15-1,"") | H26: =C26+D26 | I26: =IFERROR(H26/H15-1,"")
A27: 2025 | B27: 3 | C27: 3013.0441 | D27: 2547.9754 | E27: =C27-D27 | F27: =IFERROR(C27/C16-1,"") | G27: =IFERROR(D27/D16-1,"") | H27: =C27+D27 | I27: =IFERROR(H27/H16-1,"")
A28: 2025 | B28: 4 | C28: 4242.5935 | D28: 3559.4164 | E28: =C28-D28 | F28: =IFERROR(C28/C17-1,"") | G28: =IFERROR(D28/D17-1,"") | H28: =C28+D28 | I28: =IFERROR(H28/H17-1,"")
A29: 2025 | B29: 5 | C29: 5424.5923 | D29: 4540.0817 | E29: =C29-D29 | F29: =IFERROR(C29/C18-1,"") | G29: =IFERROR(D29/D18-1,"") | H29: =C29+D29 | I29: =IFERROR(H29/H18-1,"")
A30: 2025 | B30: 6 | C30: 6581.3934 | D30: 5528.2273 | E30: =C30-D30 | F30: =IFERROR(C30/C19-1,"") | G30: =IFERROR(D30/D19-1,"") | H30: =C30+D30 | I30: =IFERROR(H30/H19-1,"")
A31: 2025 | B31: 7 | C31: 7751.5352 | D31: 6480.7842 | E31: =C31-D31 | F31: =IFERROR(C31/C20-1,"") | G31: =IFERROR(D31/D20-1,"") | H31: =C31+D31 | I31: =IFERROR(H31/H20-1,"")
A32: 2025 | B32: 8 | C32: 9158.1271 | D32: 7476.6528 | E32: =C32-D32 | F32: =IFERROR(C32/C21-1,"") | G32: =IFERROR(D32/D21-1,"") | H32: =C32+D32 | I32: =IFERROR(H32/H21-1,"")
A33: 2025 | B33: 9 | C33: 10708.601 | D33: 8533.8394 | E33: =C33-D33 | F33: =IFERROR(C33/C22-1,"") | G33: =IFERROR(D33/D22-1,"") | H33: =C33+D33 | I33: =IFERROR(H33/H22-1,"")
A34: 2025 | B34: 10 | C34: 12230.59 | D34: 9365.7159 | E34: =C34-D34 | F34: =IFERROR(C34/C23-1,"") | G34: =IFERROR(D34/D23-1,"") | H34: =C34+D34 | I34: =IFERROR(H34/H23-1,"")
A35: 2025 | B35: 11 | C35: 13742.486 | D35: 10210.61 | E35: =C35-D35 | F35: =IFERROR(C35/C24-1,"") | G35: =IFERROR(D35/D24-1,"") | H35: =C35+D35 | I35: =IFERROR(H35/H24-1,"")
A36: 2026 | B36: 1 | C36: 1749.4153 | D36: 842.9573 | E36: =C36-D36 | F36: =IFERROR(C36/C25-1,"") | G36: =IFERROR(D36/D25-1,"") | H36: =C36+D36 | I36: =IFERROR(H36/H25-1,"")
... A42: 2026 | B42: 7 | C42: 12205.932 | D42: 7158.0634 | E42: =C42-D42 | F42: =IFERROR(C42/C31-1,"") | G42: =IFERROR(D42/D31-1,"") | H42: =C42+D42 | I42: =IFERROR(H42/H31-1,"")

Sheet Commodities
A1: Commodity exports & imports
A2: Deck slides 9-10. Source: Customs sheet 8 / 8.2 / 3, matched by HS code. Quantities in kg; amounts in thousand USD; every derived column is a formula.
A4: МЭДЭЭЛЛИЙН ОН САР / DATA AS OF: Customs (gaali.mn) — 2026-07 (CURRENT) [тайлант үе / reported month: 2026-07]
A6: Экспортын бараа (Export commodity) | B6: HS | C6: Тоо, өмнөх (Qty prev, kg) | D6: Тоо, тайлант (Qty cur, kg) | E6: Тооны өсөлт (Qty YoY) | F6: Дүн, өмнөх (Amt prev, k$) | G6: Дүн, тайлант (Amt cur, k$) | H6: Дүнгийн өсөлт (Amt YoY) | I6: сая $ (mln $) | J6: Хэмжээ (Volume, deck unit) | K6: Нэгж (Unit)
A7: Чулуун нүүрс (Coal) | B7: 2701 | C7: 41347829700 | D7: 65575819700 | E7: =IFERROR(D7/C7-1,"") | F7: 2916910.7 | G7: 4636834 | H7: =IFERROR(G7/F7-1,"") | I7: =IFERROR(G7/1000,"") | J7: =IFERROR(D7/1E9,"") | K7: mln t
A8: Зэсийн хүдэр, баяжмал (Copper concentrate) | B8: 2603 | C8: 1242814810 | D8: 1528828900 | E8: =IFERROR(D8/C8-1,"") | F8: 2879141.6 | G8: 5460531.9 | H8: =IFERROR(G8/F8-1,"") | I8: =IFERROR(G8/1000,"") | J8: =IFERROR(D8/1E6,"") | K8: thous. t
A9: Мөнгөжөөгүй алт (Gold, unwrought) | B9: 7108 | C9: 4727.9 | D9: 3060.8 | E9: =IFERROR(D9/C9-1,"") | F9: 472467.5 | G9: 482132.9 | H9: =IFERROR(G9/F9-1,"") | I9: =IFERROR(G9/1000,"") | J9: =D9 | K9: kg
A10: Төмрийн хүдэр, баяжмал (Iron ore & concentrate) | B10: 2601 | C10: 4681300519 | D10: 5162259101 | E10: =IFERROR(D10/C10-1,"") | F10: 332442 | G10: 364686.5 | H10: =IFERROR(G10/F10-1,"") | I10: =IFERROR(G10/1000,"") | J10: =IFERROR(D10/1E9,"") | K10: mln t
A11: Ноос, ноолуур (Wool & cashmere) | B11: ch51 | C11: 4461.753 | D11: 6890.7871 | E11: =IFERROR(D11/C11-1,"") | F11: 90444.824 | G11: 169775.38 | H11: =IFERROR(G11/F11-1,"") | I11: =IFERROR(G11/1000,"")
A14: Импортын бараа (Import commodities)
A15: Импортын бараа (Import commodity) | B15: HS/section | C15: Дүн, өмнөх (Amt prev, k$) | D15: Дүн, тайлант (Amt cur, k$) | E15: Дүнгийн өсөлт (Amt YoY) | F15: сая $ (mln $)
A16: Нефтийн бүтээгдэхүүн (Petroleum products) | B16: 2710 | C16: 1153491.9 | D16: 1557290 | E16: =IFERROR(D16/C16-1,"") | F16: =IFERROR(D16/1000,"")
A17: Суудлын автомашин (Passenger cars) | B17: 8703 | C17: 762229.1 | D17: 607433.2 | E17: =IFERROR(D17/C17-1,"") | F17: =IFERROR(D17/1000,"")
A18: Цахилгаан эрчим хүч (Electricity) | B18: 2716 | C18: 121600.8 | D18: 142564.8 | E18: =IFERROR(D18/C18-1,"") | F18: =IFERROR(D18/1000,"")
A19: Ачааны автомашин (Trucks) | B19: 8704 | C19: 326193.9 | D19: 269325.1 | E19: =IFERROR(D19/C19-1,"") | F19: =IFERROR(D19/1000,"")
A20: Машин, тоног төхөөрөмж (Machinery & equipment) | B20: sec16 | C20: 1346721.7 | D20: 1464975.4 | E20: =IFERROR(D20/C20-1,"") | F20: =IFERROR(D20/1000,"")
A21: Үндсэн төмөрлөг (Base metals) | B21: sec15 | C21: 590032.73 | D21: 662621.03 | E21: =IFERROR(D21/C21-1,"") | F21: =IFERROR(D21/1000,"")
A22: Хүнсний бүтээгдэхүүн (Food products) | B22: sec04 | C22: 497805.8 | D22: 531988.41 | E22: =IFERROR(D22/C22-1,"") | F22: =IFERROR(D22/1000,"")

Sheet Trade_Sections
A1: Худалдаа, хэсгээр (Trade by HS section)
A2: Full sectional detail behind slide 9. Source: Customs sheet 3, thousand USD, cumulative both years. Export and import are separate tables, each ranked by its own current-year value; YoY, share and totals are formulas.
A4: МЭДЭЭЛЛИЙН ОН САР / DATA AS OF: Customs (gaali.mn) — 2026-07 (CURRENT) [тайлант үе / reported month: 2026-07]
A6: ЭКСПОРТ, хэсгээр (EXPORT by HS section)
A7: Ranked by current-year export value. Total must equal the headline export figure on the Trade sheet.
A8: Эрэмбэ (Rank) | B8: Хэсэг (HS section) | C8: Өмнөх он (Previous, k$) | D8: Тайлант он (Current, k$) | E8: Өсөлт (YoY) | F8: Хувь (Share)
A9: 1 | B9: 05 Эрдэс бүтээгдэхүүн (Mineral products) | C9: 6848988.4 | D9: 11246857 | E9: =IFERROR(D9/C9-1,"") | F9: =IFERROR(D9/D$30,"")
A10: 2 | B10: 14 Сувд, үнэт ба хагас үнэт чулуу, үнэт металл, гоёлын зүйлс, зоос (Natural or cultured pearls, precious or semi-precious stones) | C10: 478696.28 | D10: 488697.6 | E10: =IFERROR(D10/C10-1,"") | F10: =IFERROR(D10/D$30,"")
A11: 3 | B11: 11 Нэхмэлийн материал болон нэхмэл эдлэл (Textiles and textile articles) | C11: 102222.57 | D11: 180781.5 | E11: =IFERROR(D11/C11-1,"") | F11: =IFERROR(D11/D$30,"")
A12: 4 | B12: 15 Үндсэн төмөрлөг болон түүгээр хийсэн бүтээгдэхүүн (Base metals and articles thereof) | C12: 103628 | D12: 82424.924 | E12: =IFERROR(D12/C12-1,"") | F12: =IFERROR(D12/D$30,"")
A13: 5 | B13: 16 Машин, механик тоног төхөөрөмж ба эд анги, цахилгаан хэрэгсэл, тэдг (Machinery and mechanical appliances; electrical equipments, ) | C13: 35201.891 | D13: 57189.476 | E13: =IFERROR(D13/C13-1,"") | F13: =IFERROR(D13/D$30,"")
A14: 6 | B14: 01 Амьд мал, амьтад, мал амьтдын гаралтай бүтээгдэхүүн (Live animals, animal products) | C14: 55073.601 | D14: 46187.249 | E14: =IFERROR(D14/C14-1,"") | F14: =IFERROR(D14/D$30,"")
A15: 7 | B15: 04 Хүнсний бэлэн бүтээгдэхүүн (Prepared foodstuffs) | C15: 33974.85 | D15: 44206.419 | E15: =IFERROR(D15/C15-1,"") | F15: =IFERROR(D15/D$30,"")
A16: 8 | B16: 17 Авто, агаарын ба усан замын тээврийн хэрэгсэл, тэдгээрийн эд, анги (Vehicles, aircraft, vessets and parts thereof) | C16: 15818.454 | D16: 31953.276 | E16: =IFERROR(D16/C16-1,"") | F16: =IFERROR(D16/D$30,"")
A17: 9 | B17: 02 Ургамлын гаралтай бүтээгдэхүүн (Vegetable products) | C17: 63966.442 | D17: 10468.763 | E17: =IFERROR(D17/C17-1,"") | F17: =IFERROR(D17/D$30,"")
A18: 10 | B18: 03 Мал амьтны болон ургамлын гаралтай тос, өөх (Animal or vegetable fats oils) | C18: 2301.5336 | D18: 5170.8783 | E18: =IFERROR(D18/C18-1,"") | F18: =IFERROR(D18/D$30,"")
A19: 11 | B19: 07 Хуванцар болон түүгээр хийсэн зүйлс; хаймар болон түүгээр хийсэн зү (Plastics and rubber and articles thereof) | C19: 6363.1684 | D19: 3416.1822 | E19: =IFERROR(D19/C19-1,"") | F19: =IFERROR(D19/D$30,"")
A20: 12 | B20: 18 Хараа зүй, гэрэл зураг, хэмжүүр, хяналт, эмнэлгийн багаж хэрэгсэл, (Optical, photographic, measuring, checking, medical instrume) | C20: 1737.6561 | D20: 2928.3412 | E20: =IFERROR(D20/C20-1,"") | F20: =IFERROR(D20/D$30,"")
... A28: 20 | B28: 10 Цаас болон картон, тэдгээрээр хийсэн зүйлс (Pulp of wood) | C28: 17.729025 | D28: 11.552394 | E28: =IFERROR(D28/C28-1,"") | F28: =IFERROR(D28/D$30,"")
A29: 21 | B29: Бусад (Other) | C29: 0 | D29: 0
B30: Нийт (Total) | C30: =SUM(C9:C29) | D30: =SUM(D9:D29) | E30: =IFERROR(D30/C30-1,"") | F30: =SUM(F9:F29)
A32: ИМПОРТ, хэсгээр (IMPORT by HS section)
A33: Ranked independently by current-year import value -- the order differs from the export table by design.
A34: Эрэмбэ (Rank) | B34: Хэсэг (HS section) | C34: Өмнөх он (Previous, k$) | D34: Тайлант он (Current, k$) | E34: Өсөлт (YoY) | F34: Хувь (Share)
A35: 1 | B35: 05 Эрдэс бүтээгдэхүүн (Mineral products) | C35: 1322392.9 | D35: 1795032.7 | E35: =IFERROR(D35/C35-1,"") | F35: =IFERROR(D35/D$56,"")
A36: 2 | B36: 16 Машин, механик тоног төхөөрөмж ба эд анги, цахилгаан хэрэгсэл, тэдг (Machinery and mechanical appliances; electrical equipments, ) | C36: 1346721.7 | D36: 1464975.4 | E36: =IFERROR(D36/C36-1,"") | F36: =IFERROR(D36/D$56,"")
A37: 3 | B37: 17 Авто, агаарын ба усан замын тээврийн хэрэгсэл, тэдгээрийн эд, анги (Vehicles, aircraft, vessets and parts thereof) | C37: 1383507.1 | D37: 1137721.4 | E37: =IFERROR(D37/C37-1,"") | F37: =IFERROR(D37/D$56,"")
A38: 4 | B38: 15 Үндсэн төмөрлөг болон түүгээр хийсэн бүтээгдэхүүн (Base metals and articles thereof) | C38: 590032.73 | D38: 662621.03 | E38: =IFERROR(D38/C38-1,"") | F38: =IFERROR(D38/D$56,"")
A39: 5 | B39: 04 Хүнсний бэлэн бүтээгдэхүүн (Prepared foodstuffs) | C39: 497805.8 | D39: 531988.41 | E39: =IFERROR(D39/C39-1,"") | F39: =IFERROR(D39/D$56,"")
A40: 6 | B40: 06 Химийн болон түүнтэй холбоотой үйлдвэрийн бүтээгдэхүүн (Products of the chemical or allied industries) | C40: 373473.61 | D40: 412892.77 | E40: =IFERROR(D40/C40-1,"") | F40: =IFERROR(D40/D$56,"")
A41: 7 | B41: 07 Хуванцар болон түүгээр хийсэн зүйлс; хаймар болон түүгээр хийсэн зү (Plastics and rubber and articles thereof) | C41: 218553.61 | D41: 299082.47 | E41: =IFERROR(D41/C41-1,"") | F41: =IFERROR(D41/D$56,"")
A42: 8 | B42: 13 Чулуу, гөлтгөнө, шөрмөсөн чулуу, гялтгануур болон тэдгээртэй төстэй (Articles of stone, flaster, cement, asbestos, mica or simira) | C42: 143887.18 | D42: 155066.76 | E42: =IFERROR(D42/C42-1,"") | F42: =IFERROR(D42/D$56,"")
A43: 9 | B43: 02 Ургамлын гаралтай бүтээгдэхүүн (Vegetable products) | C43: 105041.45 | D43: 146577.45 | E43: =IFERROR(D43/C43-1,"") | F43: =IFERROR(D43/D$56,"")
A44: 10 | B44: 18 Хараа зүй, гэрэл зураг, хэмжүүр, хяналт, эмнэлгийн багаж хэрэгсэл, (Optical, photographic, measuring, checking, medical instrume) | C44: 92475.566 | D44: 97453.025 | E44: =IFERROR(D44/C44-1,"") | F44: =IFERROR(D44/D$56,"")
A45: 11 | B45: 20 Аж үйлдвэрийн төрөл бүрийн бараа (Miscellaneous manufactured articles) | C45: 82908.749 | D45: 95924.827 | E45: =IFERROR(D45/C45-1,"") | F45: =IFERROR(D45/D$56,"")
A46: 12 | B46: 01 Амьд мал, амьтад, мал амьтдын гаралтай бүтээгдэхүүн (Live animals, animal products) | C46: 81569.355 | D46: 95350.447 | E46: =IFERROR(D46/C46-1,"") | F46: =IFERROR(D46/D$56,"")
... A55: 21 | B55: 21 Урлагийн бүтээл, цуглуулга хийх, зориулалтын зүйлс ба эртний үнэт д (Works of art, collectors pieces and antiques) | C55: 147.15224 | D55: 259.63553 | E55: =IFERROR(D55/C55-1,"") | F55: =IFERROR(D55/D$56,"")
B56: Нийт (Total) | C56: =SUM(C35:C55) | D56: =SUM(D35:D55) | E56: =IFERROR(D56/C56-1,"") | F56: =SUM(F35:F55)

Sheet Border_Prices
A1: Border prices (export unit values)
A2: Deck slide 11. Unit value = Δcumulative amount / Δcumulative quantity per month, from Customs sheet 8. Series fills in as monthly workbooks are cached by the ingestor.
A4: МЭДЭЭЛЛИЙН ОН САР / DATA AS OF: Customs (gaali.mn) — 2026-07 (CURRENT) [тайлант үе / reported month: 2026-07]
A6: Бараа (Commodity) | B6: Он (Year) | C6: Сар (Month) | D6: Үнэ (Price) | E6: Нэгж (Unit) | F6: Өсөлт (YoY) | G6: Basis
A7: Нүүрс (Coal) | B7: 2024 | C7: 1 | D7: 121.8 | E7: USD/t | G7: monthly
A8: Нүүрс (Coal) | B8: 2024 | C8: 2 | D8: 132.6 | E8: USD/t | G8: monthly
A9: Нүүрс (Coal) | B9: 2024 | C9: 3 | D9: 124.5 | E9: USD/t | G9: monthly
A10: Нүүрс (Coal) | B10: 2024 | C10: 4 | D10: 114.4 | E10: USD/t | G10: monthly
A11: Нүүрс (Coal) | B11: 2024 | C11: 5 | D11: 114.6 | E11: USD/t | G11: monthly
A12: Нүүрс (Coal) | B12: 2024 | C12: 6 | D12: 110.3 | E12: USD/t | G12: monthly
A13: Нүүрс (Coal) | B13: 2024 | C13: 7 | D13: 103.1 | E13: USD/t | G13: monthly
A14: Нүүрс (Coal) | B14: 2024 | C14: 8 | D14: 100.5 | E14: USD/t | G14: monthly
A15: Нүүрс (Coal) | B15: 2024 | C15: 9 | D15: 97 | E15: USD/t | G15: monthly
A16: Нүүрс (Coal) | B16: 2024 | C16: 10 | D16: 96.9 | E16: USD/t | G16: monthly
A17: Нүүрс (Coal) | B17: 2024 | C17: 11 | D17: 91.7 | E17: USD/t | G17: monthly
A18: Нүүрс (Coal) | B18: 2025 | C18: 1 | D18: 86.2 | E18: USD/t | F18: =IFERROR(D18/D7-1,"") | G18: monthly
A19: Нүүрс (Coal) | B19: 2025 | C19: 2 | D19: 81.3 | E19: USD/t | F19: =IFERROR(D19/D8-1,"") | G19: monthly
A20: Нүүрс (Coal) | B20: 2025 | C20: 3 | D20: 75.7 | E20: USD/t | F20: =IFERROR(D20/D9-1,"") | G20: monthly
A21: Нүүрс (Coal) | B21: 2025 | C21: 4 | D21: 68.8 | E21: USD/t | F21: =IFERROR(D21/D10-1,"") | G21: monthly
A22: Нүүрс (Coal) | B22: 2025 | C22: 5 | D22: 67 | E22: USD/t | F22: =IFERROR(D22/D11-1,"") | G22: monthly
A23: Нүүрс (Coal) | B23: 2025 | C23: 6 | D23: 62.5 | E23: USD/t | F23: =IFERROR(D23/D12-1,"") | G23: monthly
A24: Нүүрс (Coal) | B24: 2025 | C24: 7 | D24: 57.4 | E24: USD/t | F24: =IFERROR(D24/D13-1,"") | G24: monthly
A25: Нүүрс (Coal) | B25: 2025 | C25: 8 | D25: 56.8 | E25: USD/t | F25: =IFERROR(D25/D14-1,"") | G25: monthly
A26: Нүүрс (Coal) | B26: 2025 | C26: 9 | D26: 61.4 | E26: USD/t | F26: =IFERROR(D26/D15-1,"") | G26: monthly
A27: Нүүрс (Coal) | B27: 2025 | C27: 10 | D27: 61.6 | E27: USD/t | F27: =IFERROR(D27/D16-1,"") | G27: monthly
A28: Нүүрс (Coal) | B28: 2025 | C28: 11 | D28: 63.9 | E28: USD/t | F28: =IFERROR(D28/D17-1,"") | G28: monthly
A29: Нүүрс (Coal) | B29: 2026 | C29: 1 | D29: 64.5 | E29: USD/t | F29: =IFERROR(D29/D18-1,"") | G29: monthly
... A35: Нүүрс (Coal) | B35: 2026 | C35: 7 | D35: 79.5 | E35: USD/t | F35: =IFERROR(D35/D24-1,"") | G35: monthly
A36: Зэсийн баяжмал (Copper concentrate) | B36: 2024 | C36: 1 | D36: 1773.9 | E36: USD/t | G36: monthly
A37: Зэсийн баяжмал (Copper concentrate) | B37: 2024 | C37: 2 | D37: 1737.3 | E37: USD/t | G37: monthly
A38: Зэсийн баяжмал (Copper concentrate) | B38: 2024 | C38: 3 | D38: 1695.4 | E38: USD/t | G38: monthly
A39: Зэсийн баяжмал (Copper concentrate) | B39: 2024 | C39: 4 | D39: 1769.7 | E39: USD/t | G39: monthly
A40: Зэсийн баяжмал (Copper concentrate) | B40: 2024 | C40: 5 | D40: 1943.1 | E40: USD/t | G40: monthly
A41: Зэсийн баяжмал (Copper concentrate) | B41: 2024 | C41: 6 | D41: 2136.5 | E41: USD/t | G41: monthly
A42: Зэсийн баяжмал (Copper concentrate) | B42: 2024 | C42: 7 | D42: 2053.5 | E42: USD/t | G42: monthly
A43: Зэсийн баяжмал (Copper concentrate) | B43: 2024 | C43: 8 | D43: 2007.5 | E43: USD/t | G43: monthly
A44: Зэсийн баяжмал (Copper concentrate) | B44: 2024 | C44: 9 | D44: 1994.3 | E44: USD/t | G44: monthly
A45: Зэсийн баяжмал (Copper concentrate) | B45: 2024 | C45: 10 | D45: 2052.4 | E45: USD/t | G45: monthly
A46: Зэсийн баяжмал (Copper concentrate) | B46: 2024 | C46: 11 | D46: 2052.2 | E46: USD/t | G46: monthly
A47: Зэсийн баяжмал (Copper concentrate) | B47: 2025 | C47: 1 | D47: 1950 | E47: USD/t | F47: =IFERROR(D47/D36-1,"") | G47: monthly
A48: Зэсийн баяжмал (Copper concentrate) | B48: 2025 | C48: 2 | D48: 1985.4 | E48: USD/t | F48: =IFERROR(D48/D37-1,"") | G48: monthly
A49: Зэсийн баяжмал (Copper concentrate) | B49: 2025 | C49: 3 | D49: 2150.3 | E49: USD/t | F49: =IFERROR(D49/D38-1,"") | G49: monthly
A50: Зэсийн баяжмал (Copper concentrate) | B50: 2025 | C50: 4 | D50: 2306.5 | E50: USD/t | F50: =IFERROR(D50/D39-1,"") | G50: monthly
A51: Зэсийн баяжмал (Copper concentrate) | B51: 2025 | C51: 5 | D51: 2354.4 | E51: USD/t | F51: =IFERROR(D51/D40-1,"") | G51: monthly
A52: Зэсийн баяжмал (Copper concentrate) | B52: 2025 | C52: 6 | D52: 2478.7 | E52: USD/t | F52: =IFERROR(D52/D41-1,"") | G52: monthly
A53: Зэсийн баяжмал (Copper concentrate) | B53: 2025 | C53: 7 | D53: 2785.1 | E53: USD/t | F53: =IFERROR(D53/D42-1,"") | G53: monthly
A54: Зэсийн баяжмал (Copper concentrate) | B54: 2025 | C54: 8 | D54: 2672.8 | E54: USD/t | F54: =IFERROR(D54/D43-1,"") | G54: monthly
A55: Зэсийн баяжмал (Copper concentrate) | B55: 2025 | C55: 9 | D55: 2594.1 | E55: USD/t | F55: =IFERROR(D55/D44-1,"") | G55: monthly
A56: Зэсийн баяжмал (Copper concentrate) | B56: 2025 | C56: 10 | D56: 2808.8 | E56: USD/t | F56: =IFERROR(D56/D45-1,"") | G56: monthly
A57: Зэсийн баяжмал (Copper concentrate) | B57: 2025 | C57: 11 | D57: 2897.5 | E57: USD/t | F57: =IFERROR(D57/D46-1,"") | G57: monthly
A58: Зэсийн баяжмал (Copper concentrate) | B58: 2026 | C58: 1 | D58: 3274 | E58: USD/t | F58: =IFERROR(D58/D47-1,"") | G58: monthly
... A64: Зэсийн баяжмал (Copper concentrate) | B64: 2026 | C64: 7 | D64: 3671.7 | E64: USD/t | F64: =IFERROR(D64/D53-1,"") | G64: monthly
A65: Алт (Gold) | B65: 2024 | C65: 1 | D65: 2084.8 | E65: USD/oz | G65: monthly
A66: Алт (Gold) | B66: 2024 | C66: 3 | D66: 2120.9 | E66: USD/oz | G66: monthly
A67: Алт (Gold) | B67: 2024 | C67: 4 | D67: 2276 | E67: USD/oz | G67: monthly
A68: Алт (Gold) | B68: 2024 | C68: 5 | D68: 2393.9 | E68: USD/oz | G68: monthly
A69: Алт (Gold) | B69: 2024 | C69: 6 | D69: 2337.1 | E69: USD/oz | G69: monthly
A70: Алт (Gold) | B70: 2024 | C70: 7 | D70: 2403.9 | E70: USD/oz | G70: monthly
A71: Алт (Gold) | B71: 2024 | C71: 8 | D71: 2475.9 | E71: USD/oz | G71: monthly
A72: Алт (Gold) | B72: 2024 | C72: 9 | D72: 2579.2 | E72: USD/oz | G72: monthly
A73: Алт (Gold) | B73: 2024 | C73: 10 | D73: 2724.3 | E73: USD/oz | G73: monthly
A74: Алт (Gold) | B74: 2024 | C74: 11 | D74: 2646.6 | E74: USD/oz | G74: monthly
A75: Алт (Gold) | B75: 2025 | C75: 1 | D75: 2732.9 | E75: USD/oz | F75: =IFERROR(D75/D65-1,"") | G75: monthly
A76: Алт (Gold) | B76: 2025 | C76: 2 | D76: 2825.3 | E76: USD/oz | G76: monthly
A77: Алт (Gold) | B77: 2025 | C77: 3 | D77: 3024.1 | E77: USD/oz | F77: =IFERROR(D77/D66-1,"") | G77: monthly
A78: Алт (Gold) | B78: 2025 | C78: 4 | D78: 3261.7 | E78: USD/oz | F78: =IFERROR(D78/D67-1,"") | G78: monthly
A79: Алт (Gold) | B79: 2025 | C79: 5 | D79: 3274.6 | E79: USD/oz | F79: =IFERROR(D79/D68-1,"") | G79: monthly
A80: Алт (Gold) | B80: 2025 | C80: 6 | D80: 3384.7 | E80: USD/oz | F80: =IFERROR(D80/D69-1,"") | G80: monthly
A81: Алт (Gold) | B81: 2025 | C81: 7 | D81: 3368 | E81: USD/oz | F81: =IFERROR(D81/D70-1,"") | G81: monthly
A82: Алт (Gold) | B82: 2025 | C82: 8 | D82: 3380.1 | E82: USD/oz | F82: =IFERROR(D82/D71-1,"") | G82: monthly
A83: Алт (Gold) | B83: 2025 | C83: 9 | D83: 3520.2 | E83: USD/oz | F83: =IFERROR(D83/D72-1,"") | G83: monthly
A84: Алт (Gold) | B84: 2025 | C84: 10 | D84: 4030.2 | E84: USD/oz | F84: =IFERROR(D84/D73-1,"") | G84: monthly
A85: Алт (Gold) | B85: 2025 | C85: 11 | D85: 4142.4 | E85: USD/oz | F85: =IFERROR(D85/D74-1,"") | G85: monthly
A86: Алт (Gold) | B86: 2026 | C86: 1 | D86: 4897.5 | E86: USD/oz | F86: =IFERROR(D86/D75-1,"") | G86: monthly
A87: Алт (Gold) | B87: 2026 | C87: 2 | D87: 5180.1 | E87: USD/oz | F87: =IFERROR(D87/D76-1,"") | G87: monthly
A88: Алт (Gold) | B88: 2026 | C88: 3 | D88: 5648.5 | E88: USD/oz | F88: =IFERROR(D88/D77-1,"") | G88: monthly
... A92: Алт (Gold) | B92: 2026 | C92: 7 | D92: 4091.5 | E92: USD/oz | F92: =IFERROR(D92/D81-1,"") | G92: monthly
A93: Төмрийн хүдэр (Iron ore) | B93: 2024 | C93: 1 | D93: 79.5 | E93: USD/t | G93: monthly
A94: Төмрийн хүдэр (Iron ore) | B94: 2024 | C94: 2 | D94: 81.5 | E94: USD/t | G94: monthly
A95: Төмрийн хүдэр (Iron ore) | B95: 2024 | C95: 3 | D95: 79.6 | E95: USD/t | G95: monthly
A96: Төмрийн хүдэр (Iron ore) | B96: 2024 | C96: 4 | D96: 80 | E96: USD/t | G96: monthly
A97: Төмрийн хүдэр (Iron ore) | B97: 2024 | C97: 5 | D97: 80.8 | E97: USD/t | G97: monthly
A98: Төмрийн хүдэр (Iron ore) | B98: 2024 | C98: 6 | D98: 86.4 | E98: USD/t | G98: monthly
A99: Төмрийн хүдэр (Iron ore) | B99: 2024 | C99: 7 | D99: 84.8 | E99: USD/t | G99: monthly
A100: Төмрийн хүдэр (Iron ore) | B100: 2024 | C100: 8 | D100: 85.1 | E100: USD/t | G100: monthly
A101: Төмрийн хүдэр (Iron ore) | B101: 2024 | C101: 9 | D101: 78 | E101: USD/t | G101: monthly
A102: Төмрийн хүдэр (Iron ore) | B102: 2024 | C102: 10 | D102: 75.6 | E102: USD/t | G102: monthly
A103: Төмрийн хүдэр (Iron ore) | B103: 2024 | C103: 11 | D103: 76.7 | E103: USD/t | G103: monthly
A104: Төмрийн хүдэр (Iron ore) | B104: 2025 | C104: 1 | D104: 74.1 | E104: USD/t | F104: =IFERROR(D104/D93-1,"") | G104: monthly
A105: Төмрийн хүдэр (Iron ore) | B105: 2025 | C105: 2 | D105: 72 | E105: USD/t | F105: =IFERROR(D105/D94-1,"") | G105: monthly
A106: Төмрийн хүдэр (Iron ore) | B106: 2025 | C106: 3 | D106: 71.8 | E106: USD/t | F106: =IFERROR(D106/D95-1,"") | G106: monthly
A107: Төмрийн хүдэр (Iron ore) | B107: 2025 | C107: 4 | D107: 70.2 | E107: USD/t | F107: =IFERROR(D107/D96-1,"") | G107: monthly
A108: Төмрийн хүдэр (Iron ore) | B108: 2025 | C108: 5 | D108: 68.4 | E108: USD/t | F108: =IFERROR(D108/D97-1,"") | G108: monthly
A109: Төмрийн хүдэр (Iron ore) | B109: 2025 | C109: 6 | D109: 73 | E109: USD/t | F109: =IFERROR(D109/D98-1,"") | G109: monthly
A110: Төмрийн хүдэр (Iron ore) | B110: 2025 | C110: 7 | D110: 68.7 | E110: USD/t | F110: =IFERROR(D110/D99-1,"") | G110: monthly
A111: Төмрийн хүдэр (Iron ore) | B111: 2025 | C111: 8 | D111: 73.9 | E111: USD/t | F111: =IFERROR(D111/D100-1,"") | G111: monthly
A112: Төмрийн хүдэр (Iron ore) | B112: 2025 | C112: 9 | D112: 73.6 | E112: USD/t | F112: =IFERROR(D112/D101-1,"") | G112: monthly
A113: Төмрийн хүдэр (Iron ore) | B113: 2025 | C113: 10 | D113: 74.3 | E113: USD/t | F113: =IFERROR(D113/D102-1,"") | G113: monthly
A114: Төмрийн хүдэр (Iron ore) | B114: 2025 | C114: 11 | D114: 75.3 | E114: USD/t | F114: =IFERROR(D114/D103-1,"") | G114: monthly
A115: Төмрийн хүдэр (Iron ore) | B115: 2026 | C115: 1 | D115: 70.7 | E115: USD/t | F115: =IFERROR(D115/D104-1,"") | G115: monthly
...

Sheet External_Sector
A1: Mongolbank statistics cards
A2: Deck slide 12 (BoP, reserves, external debt, FDI) and slide 16 inputs where exposed. Every card returned by the section sweep is listed.
A4: МЭДЭЭЛЛИЙН ОН САР / DATA AS OF: Mongolbank cards — see card dates (PER-CARD) | Balance of payments — 2026-06 (LAGGED) [тайлант үе / reported month: 2026-07] ← ЭНЭ ХУУДСЫН ТОО ӨМНӨХ САРЫНХ (previous month's data)
A6: Карт (Card) | B6: Утга (Reported value, raw text) | C6: Тоон утга (Parsed value) | D6: Огноо (As of) | E6: Section file
A7: Төлбөрийн тэнцэл | B7: 567 сая $, жилийн өөрчлөлт 1,017 сая $ | C7: 567 | D7: 2026 оны 6-р сар | E7: mongolbank_external.json
A8: Гадаад хөрөнгө оруулалтын позиц | B8: -45,914 сая $, жилийн өөрчлөлт 2% | C8: -45914 | D8: 2026 оны 1-р улирал | E8: mongolbank_external.json
A9: Монгол Улсын нийт гадаад өр | B9: 40,218 сая $, жилийн өөрчлөлт 6.2% | C9: 40218 | D9: 2026 оны 1-р улирал | E9: mongolbank_external.json
A10: Гадаад валютын улсын нөөц | B10: 7,963 сая $, жилийн өөрчлөлт 48% | C10: 7963 | D10: 2026 оны 7-р сар | E10: mongolbank_external.json
A11: Шууд хөрөнгө оруулалтын статистик | B11: 37,509 сая $, жилийн өөрчлөлт 11% | C11: 37509 | D11: 2026 оны 1-р улирал | E11: mongolbank_external.json
A12: Багцын хөрөнгө оруулалтын статистик | B12: Актив: 599 сая $, Пассив: -4,834 сая $, жилийн өөрчлөлт А:8%, П: 21% | C12: 599 | D12: 2026 оны 1-р улирал | E12: mongolbank_external.json
A13: Гадаад худалдаа | B13: Тэнцэл: 5,048 сая $, жилийн өөрчлөлт 3x | C13: 5048 | D13: 2026 оны 7-р сар | E13: mongolbank_external.json
A14: Мөнгөний үзүүлэлтүүд | B14: Нийт 53.1 их наяд ₮, жилийн өөрчлөлт +25.2% | C14: 53.1 | D14: 2026 оны 7-р сар | E14: mongolbank_section_10.json
A15: Банкны салбарын тайлан тэнцэл | B15: Нийт актив 88.3 их наяд төгрөг, жилийн өөрчлөлт +25.9% | C15: 88.3 | D15: 2026 оны 7-р сар | E15: mongolbank_section_10.json
A16: Хадгаламжийн байгууллагын тойм | B16: M2 мөнгөний өсөлтийн 15.8 нэгж хувийг ГЦА, 9.5 нэгж хувийг ДЦА бүрдүүлэв. | C16: 2 | D16: 2026 оны 7-р сар | E16: mongolbank_section_10.json
A17: Банкны салбарын зээл | B17: Нийт 47.9 их наяд ₮, жилийн өөрчлөлт +13.0% | C17: 47.9 | D17: 2026 оны 7-р сар | E17: mongolbank_section_10.json
A18: Хадгаламжийн байгууллагын зээл | B18: Нийт 48.2 их наяд төгрөг, жилийн өөрчлөлт +13.0% | C18: 48.2 | D18: 2026 оны 7-р сар | E18: mongolbank_section_10.json
... A21: Ногоон зээл | B21: Нийт 2.9 их наяд ₮, жилийн өөрчлөлт +46.2% | C21: 2.9 | D21: 2026 оны 1-р улирал | E21: mongolbank_section_10.json
A24: Balance of payments — annual sums (mln USD; latest year is YTD). Source: bop_manual.xlsx
A25: Данс (Account) | B25: 2025 | C25: 2026
A26: Урсгал данс (Current account) | B26: -2119.9 | C26: 207.2
A27: Хөрөнгийн данс (Capital account) | B27: 121.2 | C27: 50
A28: Санхүүгийн данс (Financial account) | B28: -3271.2 | C28: -209.3
A29: Алдаа болон орхигдуулга (Errors & omissions) | B29: -238.2 | C29: 100.1
A30: Төлбөрийн тэнцлийн нийт дүн (Overall balance) | B30: 1034.3 | C30: 566.6
A31: Нөөц хөрөнгө (Reserve assets) | B31: 1034.3 | C31: 566.6
A34: Төлбөрийн тэнцэл, бүлгээр (Balance of payments by section and component, mln USD)
A35: Each section is followed by its own components. Indented rows sit one level deeper and are already included in the line above them, so only the section rows should be added together.
A36: Бүлэг / бүрэлдэхүүн (Section / component) | B36: 2025 I-6 (mln USD) | C36: 2026 I-6 (mln USD) | D36: Өөрчлөлт (Change)
A37: I. УРСГАЛ ДАНС | B37: -1752.49 | C37: 207.21 | D37: =C37-B37
A38: Бараа ба үйлчилгээний худалдаа | B38: -686.65 | C38: 2765.8 | D38: =C38-B38
A39: 1. Бараа | B39: 720.68 | C39: 4513.47 | D39: =C39-B39
A40: 2. Үйлчилгээ | B40: -1407.32 | C40: -1747.68 | D40: =C40-B40
A41: 3. Анхдагч орлого | B41: -1213.19 | C41: -2700.41 | D41: =C41-B41
A42: 4. Хоёрдогч орлого | B42: 147.34 | C42: 141.83 | D42: =C42-B42
A43: II. ХӨРӨНГИЙН ДАНС | B43: 50.68 | C43: 49.95 | D43: =C43-B43
A44: 1. Үйлдвэрлэхгүй санхүүгийн бус хөрөнгийн өсөлт (Дт)/ бууралт (Кр) | B44: 0 | C44: 0 | D44: =C44-B44
A45: 2. Хөрөнгийн шилжүүлэг | B45: 50.68 | C45: 49.95 | D45: =C45-B45
A46: III. САНХҮҮГИЙН ДАНС | B46: -1257.23 | C46: -209.3 | D46: =C46-B46
A47: 1. Шууд хөрөнгө оруулалт | B47: -916.33 | C47: -1232.67 | D47: =C47-B47
A48: 2. Багцын хөрөнгө оруулалт | B48: -163.55 | C48: -155.54 | D48: =C48-B48
... A55: 3. Тусгай санхүүжилт | B55: 0 | C55: 0 | D55: =C55-B55

Sheet Banking
A1: Banking sector — consolidated bank balance sheet
A2: Deck slide 16. Source: Mongolbank 'Банкуудын нэгдсэн тайлан тэнцэл' xlsx (million MNT). change measured 2025.07.31 -> 2026.07.31 (earliest column in the report; not necessarily 31 Dec)
A4: МЭДЭЭЛЛИЙН ОН САР / DATA AS OF: Bank balance sheet — 2026-07 (CURRENT) | Deposit tree — 2026-07 (CURRENT) [тайлант үе / reported month: 2026-07]
A6: Үзүүлэлт (Indicator) | B6: Түвшин 2025.07.31 (Level, mln ₮) | C6: Түвшин 2026.07.31 (Level, mln ₮) | D6: Өөрчлөлт (Change since first col) | E6: их наяд ₮ (Latest, tln ₮)
A7: Нийт актив (Total assets) | B7: 70133414 | C7: 88314736 | D7: =IFERROR(C7/B7-1,"") | E7: =IFERROR(C7/1E6,"")
A8: Дотоодын нийт зээл (Total loans, domestic) | B8: 42795499 | C8: 48448814 | D8: =IFERROR(C8/B8-1,"") | E8: =IFERROR(C8/1E6,"")
A9: Төв банкны үнэт цаас (Central bank securities) | B9: 8124839.7 | C9: 13950234 | D9: =IFERROR(C9/B9-1,"") | E9: =IFERROR(C9/1E6,"")
A10: Харилцах, хадгаламж (Current accounts + deposits) | B10: 39711140 | C10: 49532868 | D10: =IFERROR(C10/B10-1,"") | E10: =IFERROR(C10/1E6,"")
A11: Анхаарал хандуулах зээл (Past-due / special mention) | B11: 1855928.4 | C11: 1236133.8 | D11: =IFERROR(C11/B11-1,"") | E11: =IFERROR(C11/1E6,"")
A12: Чанаргүй зээл (Non-performing loans) | B12: 1874067.3 | C12: 2242577.9 | D12: =IFERROR(C12/B12-1,"") | E12: =IFERROR(C12/1E6,"")
A13: Өөрийн хөрөнгө (Equity) | B13: 7709800.5 | C13: 8776028.9 | D13: =IFERROR(C13/B13-1,"") | E13: =IFERROR(C13/1E6,"")
A16: Сар бүрийн түвшин (Monthly levels, mln ₮) per balance-sheet metric
A17: Үзүүлэлт (Metric) | B17: 2025.07.31 | C17: 2025.12.31 | D17: 2026.06.30 | E17: 2026.07.31
A18: Нийт актив (Total assets) | B18: 70133414 | C18: 85425638 | D18: 92008677 | E18: 88314736
A19: Дотоодын нийт зээл (Total loans, domestic) | B19: 42795499 | C19: 44237247 | D19: 49478700 | E19: 48448814
A20: Төв банкны үнэт цаас (Central bank securities) | B20: 8124839.7 | C20: 10973337 | D20: 13939535 | E20: 13950234
A21: Харилцах, хадгаламж (Current accounts + deposits) | B21: 39711140 | C21: 42973445 | D21: 49437268 | E21: 49532868
A22: Анхаарал хандуулах зээл (Past-due / special mention) | B22: 1855928.4 | C22: 1492307.9 | D22: 1215900.1 | E22: 1236133.8
A23: Чанаргүй зээл (Non-performing loans) | B23: 1874067.3 | C23: 1949864.2 | D23: 2169931 | E23: 2242577.9
A24: Өөрийн хөрөнгө (Equity) | B24: 7709800.5 | C24: 8455129.5 | D24: 8641748.7 | E24: 8776028.9
A27: ХАРИЛЦАХ, ХАДГАЛАМЖ (deposits and current accounts, mln ₮) — Нийт пассив breakdown
A28: Each block splits by currency, then by tenor for savings, then by holder. Indented rows are already included in the line above them, so only the two top-level blocks add to total deposits. Source: deposits_export.json
A29: Үзүүлэлт (Item) | B29: 2025-01 | C29: 2025-02 | D29: 2025-03 | E29: 2025-04 | F29: 2025-05 | G29: 2025-06 | H29: 2025-07 | I29: 2025-08 | J29: 2025-09 | K29: 2025-10 | L29: 2025-11 | M29: 2025-12 | N29: 2026-01 | O29: 2026-02 | P29: 2026-03 | Q29: 2026-04 | R29: 2026-05 | S29: 2026-06 | T29: 2026-07 | U29: Өөрчлөлт (2026-06→2026-07) | V29: Эзлэх (Share)
A30: Аж ахуйн нэгж, иргэдийн харилцах | B30: 13150202 | C30: 12526979 | D30: 12182996 | E30: 12183805 | F30: 11862276 | G30: 12752707 | H30: 12285032 | I30: 13326207 | J30: 13130568 | K30: 13346462 | L30: 13425797 | M30: 13489327 | N30: 13507453 | O30: 14269744 | P30: 14780196 | Q30: 15942892 | R30: 16502834 | S30: 17979271 | T30: 17411336 | U30: =T30-S30 | V30: =IFERROR(T30/T$64,"")
A31: Төгрөгийн харилцах | B31: 9610957.4 | C31: 8941977.9 | D31: 8886313.7 | E31: 8628760.2 | F31: 8408479 | G31: 9305774.2 | H31: 8883870.2 | I31: 8929440.9 | J31: 9104660.2 | K31: 9544672.8 | L31: 9610032.9 | M31: 9643437.2 | N31: 9588710.6 | O31: 9214996.3 | P31: 9538602.1 | Q31: 10811126 | R31: 11090744 | S31: 11950516 | T31: 11007116 | U31: =T31-S31 | V31: =IFERROR(T31/T$64,"")
A32: Улсын байгууллага | B32: 2394583 | C32: 1458178.2 | D32: 1661321.8 | E32: 1255228.4 | F32: 1080688.8 | G32: 1038442.3 | H32: 994394.91 | I32: 1153962.8 | J32: 1014711.5 | K32: 1194217.5 | L32: 1573649 | M32: 1102172.4 | N32: 1640677.4 | O32: 1446935.2 | P32: 1323890.1 | Q32: 1989398.2 | R32: 1909453.1 | S32: 1934855.6 | T32: 1575441 | U32: =T32-S32 | V32: =IFERROR(T32/T$64,"")
A33: Хувийн байгууллага | B33: 3637348.1 | C33: 3706645 | D33: 3768232.1 | E33: 3543364 | F33: 3391993.4 | G33: 4062893.9 | H33: 3632904.5 | I33: 3732414 | J33: 3919103.4 | K33: 4173581.3 | L33: 4169000.6 | M33: 4447184.3 | N33: 4161537 | O33: 4085926.4 | P33: 4451591 | Q33: 4432960.6 | R33: 4702978.4 | S33: 5126683.3 | T33: 4673399 | U33: =T33-S33 | V33: =IFERROR(T33/T$64,"")
A34: Иргэд | B34: 3414214.4 | C34: 3616125.7 | D34: 3267647.6 | E34: 3632470.6 | F34: 3760464.6 | G34: 4017040.8 | H34: 4077990.3 | I34: 3844764.3 | J34: 3980571.7 | K34: 3991996.6 | L34: 3691658.9 | M34: 3914085.2 | N34: 3616843.5 | O34: 3490505.1 | P34: 3566286 | Q34: 4174335.9 | R34: 4253190.1 | S34: 4666194.8 | T34: 4552967 | U34: =T34-S34 | V34: =IFERROR(T34/T$64,"")
A35: Бусад байгууллага | B35: 164811.98 | C35: 161028.93 | D35: 189112.07 | E35: 197697.17 | F35: 175332.28 | G35: 187397.13 | H35: 178580.43 | I35: 198299.69 | J35: 190273.59 | K35: 184877.32 | L35: 175724.47 | M35: 179995.24 | N35: 169652.73 | O35: 191629.47 | P35: 196834.96 | Q35: 214430.82 | R35: 225122.45 | S35: 222782.72 | T35: 205308.9 | U35: =T35-S35 | V35: =IFERROR(T35/T$64,"")
A36: Гадаад валютын харилцах | B36: 3539245.1 | C36: 3585001.3 | D36: 3296682 | E36: 3555044.6 | F36: 3453797.4 | G36: 3446932.9 | H36: 3401162.3 | I36: 4396766.2 | J36: 4025908.1 | K36: 3801789.8 | L36: 3815764.4 | M36: 3845890.1 | N36: 3918742.7 | O36: 5054747.9 | P36: 5241593.5 | Q36: 5131766.8 | R36: 5412090.4 | S36: 6028754.6 | T36: 6404220 | U36: =T36-S36 | V36: =IFERROR(T36/T$64,"")
A37: Улсын байгууллага | B37: 488278.01 | C37: 701318.45 | D37: 468943.32 | E37: 517242.19 | F37: 366296.97 | G37: 357136.95 | H37: 389598.76 | I37: 413972.71 | J37: 547029.83 | K37: 443306.94 | L37: 536620.06 | M37: 593736.37 | N37: 645669.89 | O37: 1005684 | P37: 1583649.6 | Q37: 1335674.2 | R37: 1783152.1 | S37: 2282165.1 | T37: 2788586 | U37: =T37-S37 | V37: =IFERROR(T37/T$64,"")
A38: Хувийн байгууллага | B38: 2415739.6 | C38: 2321438.8 | D38: 2255461.3 | E38: 2409478 | F38: 2460393.8 | G38: 2477838.9 | H38: 2379010.8 | I38: 3362543.5 | J38: 2820946.8 | K38: 2743361.1 | L38: 2699642.5 | M38: 2692384.4 | N38: 2725192 | O38: 3498068.9 | P38: 3095521.7 | Q38: 3233269.6 | R38: 3066659.4 | S38: 3161963.9 | T38: 2992669 | U38: =T38-S38 | V38: =IFERROR(T38/T$64,"")
A39: Иргэд | B39: 580477.04 | C39: 506309.6 | D39: 515740.42 | E39: 552304.17 | F39: 558724.39 | G39: 546411.25 | H39: 567802.79 | I39: 555747.94 | J39: 576992.85 | K39: 546096.2 | L39: 511962.4 | M39: 502331.43 | N39: 487410.88 | O39: 488599.78 | P39: 489366.56 | Q39: 487091.72 | R39: 489233.06 | S39: 514731.04 | T39: 553111.4 | U39: =T39-S39 | V39: =IFERROR(T39/T$64,"")
A40: Бусад байгууллага | B40: 54750.45 | C40: 55934.43 | D40: 56536.95 | E40: 76020.32 | F40: 68382.21 | G40: 65545.85 | H40: 64749.98 | I40: 64502.01 | J40: 80938.62 | K40: 69025.56 | L40: 67539.46 | M40: 57437.92 | N40: 60470 | O40: 62395.24 | P40: 73055.64 | Q40: 75731.17 | R40: 73045.88 | S40: 69894.57 | T40: 69853.44 | U40: =T40-S40 | V40: =IFERROR(T40/T$64,"")
A41: Аж ахуйн нэгж, иргэдийн хадгаламж | B41: 25401797 | C41: 25923542 | D41: 26059834 | E41: 26134860 | F41: 26478853 | G41: 26916227 | H41: 27426108 | I41: 27423716 | J41: 27635390 | K41: 28308655 | L41: 28514308 | M41: 29484118 | N41: 29439824 | O41: 30087905 | P41: 30426832 | Q41: 30719195 | R41: 31330148 | S41: 31457997 | T41: 32121532 | U41: =T41-S41 | V41: =IFERROR(T41/T$64,"")
... A63: Бусад байгууллага | B63: 22144.21 | C63: 18759.42 | D63: 21973.18 | E63: 21502.12 | F63: 26636.89 | G63: 26348.28 | H63: 26362.2 | I63: 25533.05 | J63: 25395.08 | K63: 35200.45 | L63: 34756.06 | M63: 32689.96 | N63: 32967.29 | O63: 32238.1 | P63: 30407.71 | Q63: 30077.83 | R63: 27894 | S63: 26197.04 | T63: 27912.79 | U63: =T63-S63 | V63: =IFERROR(T63/T$64,"")
A64: Нийт харилцах, хадгаламж (Total deposits) | B64: =B30+B41 | C64: =C30+C41 | D64: =D30+D41 | E64: =E30+E41 | F64: =F30+F41 | G64: =G30+G41 | H64: =H30+H41 | I64: =I30+I41 | ... T64: =T30+T41

Sheet Loan_Detail
A1: Банкны салбарын зээл, дэлгэрэнгүй (Bank loans in detail)
A2: Mongolbank monthly loan report, 2026-07 (million MNT). The report is a flow statement, so the change in the loan book is decomposed rather than estimated. Growth, shares and totals are formulas.
A4: МЭДЭЭЛЛИЙН ОН САР / DATA AS OF: Bank loan report — 2026-07 (CURRENT) [тайлант үе / reported month: 2026-07]
A6: 0. ҮЗҮҮЛЭЛТҮҮД (indicators as published on stat.mongolbank.mn — Банкны салбарын зээл)
A7: Same figures as the portal's indicator list. Per the report's own Заавар sheet, 'хугацаа хэтэрсэн' is the special-mention class and 'чанаргүй' is substandard + doubtful + loss.
A8: Үзүүлэлт (Indicator) | B8: Нийт (Total) | C8: Үүнээс: төгрөгийн зээл (of which MNT) | D8: Валютын хувь (FX share) | E8: Нийт зээлд эзлэх (Share of book)
A9: Зээлийн үлдэгдэл (Loan balance) | B9: 47876124 | C9: 45062486 | D9: =IFERROR(1-C9/B9,"") | E9: =IFERROR(B9/B$9,"")
A10: Хугацаа хэтэрсэн зээлийн үлдэгдэл (Past due) | B10: 1236542.7 | C10: 1143146.3 | D10: =IFERROR(1-C10/B10,"") | E10: =IFERROR(B10/B$9,"")
A11: Чанаргүй зээлийн үлдэгдэл (Non-performing) | B11: 2510344.4 | C11: 2297151.8 | D11: =IFERROR(1-C11/B11,"") | E11: =IFERROR(B11/B$9,"")
A12: Төслөөр хэрэгжсэн зээлийн үлдэгдэл (Project loans) | B12: 3053100.4 | C12: 2968492.1 | D12: =IFERROR(1-C12/B12,"") | E12: =IFERROR(B12/B$9,"")
A14: 1. ЗЭЭЛИЙН ӨСӨЛТИЙН ЗАДАРГАА (how the loan book grew)
A15: Үзүүлэлт (Flow) | B15: Дүн (mln MNT)
A16: Эхний үлдэгдэл (Opening balance) | B16: 48957222
A17: + Олгосон зээл (Loans disbursed) | B17: 5840363.7
A18: − Төлөгдсөн зээл (Loans repaid) | B18: -6188131.5
A19: − Сангаас хаагдсан (Written off) | B19: 0
A20: ± Ханшийн тэгшитгэл (FX revaluation) | B20: 12789.25
A21: ± Бусад гүйлгээ (Other movements) | B21: -746119.35
A22: Эцсийн үлдэгдэл (Closing balance, computed) | B22: =SUM(B16:B21)
A23: Тайлант эцсийн үлдэгдэл (Closing, as reported) | B23: 47876124
A24: Зөрүү (Residual — must be 0) | B24: =B22-B23
A25: Өөрчлөлт (Net change) | B25: =B23-B16
A26: Өсөлт, сараар (Growth, month on month) | B26: =IFERROR(B23/B16-1,"")
A27: Өсөлт, жилээр (Growth YoY vs 2025-07) | B27: 0.1302
A29: 2. САЛБАРААР (by economic sector — what drove it)
A30: Ranked by contribution to the month's growth. The pp column sums to the total growth rate above.
A31: Код | B31: Салбар (Sector) | C31: Эхний үлдэгдэл (Opening) | D31: Эцсийн үлдэгдэл (Closing) | E31: Өөрчлөлт (Change) | F31: Хувь нэмэр (pp) | G31: Эзлэх (Share) | H31: Үүнээс: төгрөгийн (of which MNT) | I31: Жилийн өсөлт (YoY)
A32: H | B32: ТЭЭВЭР, АГУУЛАХЫН ҮЙЛ АЖИЛЛАГАА | C32: 1489751.3 | D32: 1556925.5 | E32: =D32-C32 | F32: =IFERROR((D32-C32)/C$54*100,"") | G32: =IFERROR(D32/D$54,"") | H32: 1026811.8 | I32: 0.35
A33: B | B33: УУЛ УУРХАЙ, ОЛБОРЛОЛТ | C33: 2684186.8 | D33: 2731598.2 | E33: =D33-C33 | F33: =IFERROR((D33-C33)/C$54*100,"") | G33: =IFERROR(D33/D$54,"") | H33: 1725309.5 | I33: 0.14
A34: P | B34: БОЛОВСРОЛ | C34: 485784.95 | D34: 499339.79 | E34: =D34-C34 | F34: =IFERROR((D34-C34)/C$54*100,"") | G34: =IFERROR(D34/D$54,"") | H34: 499305.85 | I34: 0.206
A35: I | B35: ЗОЧИД БУУДАЛ, БАЙР, СУУЦ БОЛОН НИЙТИЙН ХООЛНЫ ҮЙЛЧИЛГЭЭ | C35: 929616.11 | D35: 942750.19 | E35: =D35-C35 | F35: =IFERROR((D35-C35)/C$54*100,"") | G35: =IFERROR(D35/D$54,"") | H35: 912851.59 | I35: 0.512
A36: N | B36: УДИРДЛАГЫН БОЛОН ДЭМЖЛЭГ ҮЗҮҮЛЭХ ҮЙЛ АЖИЛЛАГАА | C36: 243510.57 | D36: 251717.28 | E36: =D36-C36 | F36: =IFERROR((D36-C36)/C$54*100,"") | G36: =IFERROR(D36/D$54,"") | H36: 235904.78 | I36: 0.822
A37: T | B37: ХҮН ХӨЛСЛӨН АЖИЛЛУУЛДАГ ӨРХИЙН ҮЙЛ АЖИЛЛАГАА; ӨРХИЙН ӨӨРИЙН ХЭРЭГЛЭЭНД | C37: 185981.73 | D37: 189401.77 | E37: =D37-C37 | F37: =IFERROR((D37-C37)/C$54*100,"") | G37: =IFERROR(D37/D$54,"") | H37: 188143.89 | I37: 0.637
A38: J | B38: МЭДЭЭЛЭЛ, ХОЛБОО | C38: 128382.22 | D38: 131671.2 | E38: =D38-C38 | F38: =IFERROR((D38-C38)/C$54*100,"") | G38: =IFERROR(D38/D$54,"") | H38: 131666.01 | I38: 0.065
A39: R | B39: УРЛАГ, ҮЗВЭР, ТОГЛООМ НААДАМ | C39: 94451.757 | D39: 97606.089 | E39: =D39-C39 | F39: =IFERROR((D39-C39)/C$54*100,"") | G39: =IFERROR(D39/D$54,"") | H39: 97606.089 | I39: 0.597
A40: Q | B40: ХҮНИЙ ЭРҮҮЛ МЭНД, НИЙГМИЙН ХАЛАМЖИЙН ҮЙЛ АЖИЛЛАГАА | C40: 384882.6 | D40: 387430.24 | E40: =D40-C40 | F40: =IFERROR((D40-C40)/C$54*100,"") | G40: =IFERROR(D40/D$54,"") | H40: 387430.24 | I40: 0.209
A41: M | B41: МЭРГЭЖЛИЙН, ШИНЖЛЭХ УХААН БОЛОН ТЕХНИКИЙН ҮЙЛ АЖИЛЛАГАА | C41: 58871.317 | D41: 58722.832 | E41: =D41-C41 | F41: =IFERROR((D41-C41)/C$54*100,"") | G41: =IFERROR(D41/D$54,"") | H41: 51525.093 | I41: 0.387
A42: O | B42: ТӨРИЙН УДИРДЛАГА, БАТЛАН ХАМГААЛАХ ҮЙЛ АЖИЛЛАГАА, АЛБАН ЖУРМЫН НИЙГМИЙ | C42: 11436.225 | D42: 11057.308 | E42: =D42-C42 | F42: =IFERROR((D42-C42)/C$54*100,"") | G42: =IFERROR(D42/D$54,"") | H42: 11057.308 | I42: 0.054
A43: U | B43: ОЛОН УЛСЫН БАЙГУУЛЛАГА, СУУРИН ТӨЛӨӨЛӨГЧИЙН ҮЙЛ АЖИЛЛАГАА | C43: 32534.359 | D43: 31421.784 | E43: =D43-C43 | F43: =IFERROR((D43-C43)/C$54*100,"") | G43: =IFERROR(D43/D$54,"") | H43: 31421.784 | I43: -0.426
... A53: L | B53: ҮЛ ХӨДЛӨХ ХӨРӨНГИЙН ҮЙЛ АЖИЛЛАГАА | C53: 7819687.9 | D53: 7204175.3 | E53: =D53-C53 | F53: =IFERROR((D53-C53)/C$54*100,"") | G53: =IFERROR(D53/D$54,"") | H53: 7198587.2 | I53: 0.102
B54: Нийт (Total) | C54: =SUM(C32:C53) | D54: =SUM(D32:D53) | E54: =SUM(E32:E53) | F54: =SUM(F32:F53) | G54: =SUM(G32:G53) | H54: =SUM(H32:H53)
A56: 2b. Нэрлэсэн зээлүүд (named loan products, already included in their sector above)
A57: Код | B57: Зээл (Product) | C57: Эхний үлдэгдэл (Opening) | D57: Эцсийн үлдэгдэл (Closing) | E57: Өөрчлөлт (Change)
A58: A | B58: Үүнээс: а. Хөдөө аж ахуй | C58: 506539.43 | D58: 491651.93 | E58: =D58-C58
A59: A | B59: б. Газар тариалан | C59: 973094.75 | D59: 959154.79 | E59: =D59-C59
A60: P | B60: Үүнээс: Сургалтын зээл (дотоод) | C60: 1036.7608 | D60: 1042.2752 | E60: =D60-C60
A61: Q | B61: Үүнээс: 6.Эмчилгээний төлбөрийн зээл (дотоод) | C61: 0 | D61: 0 | E61: =D61-C61
A62: V | B62: Үүнээс: 1. Цалингийн зээл | C62: 6325959.8 | D62: 6281646.2 | E62: =D62-C62
A63: V | B63: Үүнээс: 2. Тэтгэврийн зээл | C63: 3157630.2 | D63: 3184073 | E63: =D63-C63
A64: V | B64: Үүнээс: 3.Картын зээл | C64: 209288.41 | D64: 209443.47 | E64: =D64-C64
A65: V | B65: Үүнээс: 4.Автомашины зээл | C65: 60731.215 | D65: 59173.796 | E65: =D65-C65
A66: V | B66: Үүнээс: 5.Өрхийн хэрэглээнд зориулсан зээл | C66: 648662.51 | D66: 641637.56 | E66: =D66-C66
A67: V | B67: Үүнээс: 6.Эмчилгээний төлбөрийн зээл (гадаад) | C67: 4.6185722 | D67: 4.2133436 | E67: =D67-C67
A68: V | B68: Үүнээс: 7.Сургалтын зээл (гадаад) | C68: 240.51239 | D68: 217.79929 | E68: =D68-C68
A69: V | B69: Үүнээс: 8.Малчны зээл | C69: 1208059.2 | D69: 1235685.7 | E69: =D69-C69
A70: V | B70: Үүнээс: 9.Хадгаламж, данс барьцаалсан зээл | C70: 1805747.4 | D70: 1752305.8 | E70: =D70-C70
A72: 3. ЧАНАРААР (loan quality and NPL)
A73: Ангилал (Class) | B73: Эхний үлдэгдэл (Opening) | C73: Эцсийн үлдэгдэл (Closing) | D73: Өөрчлөлт (Change) | E73: Эзлэх (Share)
A74: Хэвийн зээл (Performing) | B74: 45300629 | C74: 44129237 | D74: =C74-B74 | E74: =IFERROR(C74/47876124.33761412,"")
A75: Анхаарал хандуулах зээл (Special mention) | B75: 1216315.4 | C75: 1236542.7 | D75: =C75-B75 | E75: =IFERROR(C75/47876124.33761412,"")
A76: Хэвийн бус зээл (Substandard) | B76: 450067.43 | C76: 460655.33 | D76: =C76-B76 | E76: =IFERROR(C76/47876124.33761412,"")
A77: Эргэлзээтэй зээл (Doubtful) | B77: 424153.67 | C77: 463114.85 | D77: =C77-B77 | E77: =IFERROR(C77/47876124.33761412,"")
A78: Муу зээл (Loss) | B78: 1566057.1 | C78: 1586574.2 | D78: =C78-B78 | E78: =IFERROR(C78/47876124.33761412,"")
A79: Сан (Provisions) | B79: 2061959.9 | C79: 2137590.1 | D79: =C79-B79 | E79: =IFERROR(C79/47876124.33761412,"")
A80: Чанаргүй зээл (NPL = substandard + doubtful + loss) | C80: =C76+C77+C78 | E80: =IFERROR(C80/47876124.33761412,"")
A82: 4. ЗЭЭЛДЭГЧЭЭР (by borrower type)
A83: Зээлдэгч (Borrower) | B83: Эхний үлдэгдэл (Opening) | C83: Эцсийн үлдэгдэл (Closing) | D83: Өөрчлөлт (Change) | E83: Өсөлт (Growth) | F83: Эзлэх (Share) | G83: Зээлдэгчийн тоо (Count)
A84: Хувийн байгууллага (Private companies) | B84: 18653496 | C84: 19540429 | D84: =C84-B84 | E84: =IFERROR(C84/B84-1,"") | F84: =IFERROR(C84/C$89,"") | G84: 19770
A85: Улсын байгууллага (State organisations) | B85: 286116.6 | C85: 369928.19 | D85: =C85-B85 | E85: =IFERROR(C85/B85-1,"") | F85: =IFERROR(C85/C$89,"") | G85: 87
A86: Бусад санхүүгийн байгууллага (Other financial corp.) | B86: 292866.81 | C86: 275006.89 | D86: =C86-B86 | E86: =IFERROR(C86/B86-1,"") | F86: =IFERROR(C86/C$89,"") | G86: 145
A87: Иргэд (Individuals) | B87: 28829078 | C87: 28117723 | D87: =C87-B87 | E87: =IFERROR(C87/B87-1,"") | F87: =IFERROR(C87/C$89,"") | G87: 2216720
A88: Бусад (Other) | B88: 8731.9215 | C88: 9357.8343 | D88: =C88-B88 | E88: =IFERROR(C88/B88-1,"") | F88: =IFERROR(C88/C$89,"") | G88: 46
A89: Нийт (Total) | B89: =SUM(B84:B88) | C89: =SUM(C84:C88) | D89: =SUM(D84:D88) | G89: =SUM(G84:G88)
A91: 5. ХҮҮ, ХУГАЦАА (weighted average, total book)
A92: Үзүүлэлт (Measure) | B92: Төгрөг (MNT) | C92: Гадаад валют (FX)
A93: Тайлант сард олгосон зээлийн хүү (New lending rate) | B93: 0.17245236 | C93: 0.11049616
A94: Үлдэгдэл зээлийн хүү (Rate on outstanding stock) | B94: 0.1696336 | C94: 0.10777622
A95: Үлдэгдэл зээлийн хугацаа, сар (Maturity, months) | B95: 54
A97: 6. САРААР (monthly series — self-extending)
A98: Сар (Month) | B98: Эхний үлдэгдэл (Opening) | C98: Эцсийн үлдэгдэл (Closing) | D98: Олгосон (Disbursed) | E98: Төлөгдсөн (Repaid) | F98: Өсөлт (MoM)
A99: 2025-07 | B99: 42224382 | C99: 42360924 | D99: 5233344.6 | E99: 5098397.7 | F99: =IFERROR(C99/B99-1,"")
A100: 2025-08 | B100: 42360924 | C100: 42294729 | D100: 5245403.1 | E100: 4707909.1 | F100: =IFERROR(C100/B100-1,"")
A101: 2025-09 | B101: 42294729 | C101: 42726783 | D101: 5615405 | E101: 5177882.4 | F101: =IFERROR(C101/B101-1,"")
A102: 2025-10 | B102: 42726783 | C102: 43460369 | D102: 6102414.5 | E102: 5363011.4 | F102: =IFERROR(C102/B102-1,"")
A103: 2025-11 | B103: 43460369 | C103: 43107326 | D103: 4993547.3 | E103: 4815168.6 | F103: =IFERROR(C103/B103-1,"")
A104: 2025-12 | B104: 43107326 | C104: 43751570 | D104: 6670921.1 | E104: 6025240.6 | F104: =IFERROR(C104/B104-1,"")
A105: 2026-01 | B105: 43751570 | C105: 43908126 | D105: 5497105.1 | E105: 5348273.7 | F105: =IFERROR(C105/B105-1,"")
A106: 2026-02 | B106: 43908126 | C106: 43889722 | D106: 4260443.5 | E106: 4278682.5 | F106: =IFERROR(C106/B106-1,"")
A107: 2026-03 | B107: 43889722 | C107: 45005551 | D107: 5969526.8 | E107: 4845873.5 | F107: =IFERROR(C107/B107-1,"")
A108: 2026-04 | B108: 45005551 | C108: 45963701 | D108: 6829824.7 | E108: 5869933 | F108: =IFERROR(C108/B108-1,"")
A109: 2026-05 | B109: 45963701 | C109: 47259969 | D109: 7268851.7 | E109: 5977317 | F109: =IFERROR(C109/B109-1,"")
A110: 2026-06 | B110: 47259969 | C110: 48957222 | D110: 8102758.6 | E110: 6381495.7 | F110: =IFERROR(C110/B110-1,"")
A111: 2026-07 | B111: 48957222 | C111: 47876124 | D111: 5840363.7 | E111: 6188131.5 | F111: =IFERROR(C111/B111-1,"")

Sheet Real_Sector
A1: Бодит салбарууд (Real sector — trade, services, construction, industry)
A2: Deck slides 16-21. Source: NSO 1212.mn. Cumulative from the start of the year (өссөн дүнгээр); growth is year on year on that cumulative; each component's contribution is its share of the year-on-year change, so the contributions sum to the headline growth. Money in сая төг.
A4: МЭДЭЭЛЛИЙН ОН САР / DATA AS OF: 2026-06, 2026-07, 2026-Q2 [тайлант үе / reported month: 2026-07] ← ЗАРИМ ХҮСНЭГТ ӨМНӨХ САРЫНХ (some tables lag; each table's own month is on its header line)
A6: Худалдааны салбарын нийт борлуулалт — 2026-06
A7: Сараар, өссөн дүнгээр · нийт 33,813,378.1 сая төг · өмнөх оны мөн үе 30,720,541.5
A8: Бүрэлдэхүүн (Component) | B8: Өмнөх он (Prev, cum.) | C8: Тайлант он (Cur, cum.) | D8: Өөрчлөлт (Change) | E8: Хувь нэмэр (Contribution, pp) | F8: Жилийн өсөлт (YoY)
A9: Улаанбаатар | B9: 26499027 | C9: 29139515 | D9: =C9-B9 | E9: 8.59519 | F9: 0.0996
A10: Төвийн бүс | B10: 2096239.7 | C10: 2364455.7 | D10: =C10-B10 | E10: 0.873084 | F10: 0.128
A11: Хангайн бүс | B11: 1024414.2 | C11: 1144447.8 | D11: =C11-B11 | E11: 0.390727 | F11: 0.1172
A12: Баруун бүс | B12: 587458.34 | C12: 624672.09 | D12: =C12-B12 | E12: 0.121136 | F12: 0.0633
A13: Зүүн бүс | B13: 513402.67 | C13: 540287.03 | D13: =C13-B13 | E13: 0.087513 | F13: 0.0524
A14: Нийт (Total — must equal the headline growth) | B14: =SUM(B9:B13) | C14: =SUM(C9:C13) | D14: =C14-B14 | E14: =SUM(E9:E13) | F14: =IFERROR(C14/B14-1,"")
A15: Салбарын өсөлт (Headline growth, YoY) | E15: 10.0677
A17: Цуваа (series for the chart)
A18: Үе (Period) | B18: Өссөн дүн (Cumulative) | C18: Тухайн үе (Single period)
A19: 2017-01 | B19: 879245.63 | C19: 879245.63
A20: 2017-02 | B20: 1894490.4 | C20: 1015244.8
A21: 2017-03 | B21: 2990107 | C21: 1095616.6
A22: 2017-04 | B22: 4104048.5 | C22: 1113941.5
A23: 2017-05 | B23: 5408122.6 | C23: 1304074.1
A24: 2017-06 | B24: 6861042.3 | C24: 1452919.7
A25: 2017-07 | B25: 8190656.5 | C25: 1329614.2
A26: 2017-08 | B26: 9582407.8 | C26: 1391751.2
A27: 2017-09 | B27: 11073703 | C27: 1491295.1
A28: 2017-10 | B28: 12570370 | C28: 1496667
A29: 2017-11 | B29: 13954734 | C29: 1384364.2
A30: 2017-12 | B30: 15968766 | C30: 2014032.1
... A132: 2026-06 | B132: 33813378 | C132: 6827675.3
A135: Зочид буудлын салбарын орлого — 2026-06
A136: Сараар, өссөн дүнгээр · нийт 154,326.1 сая төг · өмнөх оны мөн үе 137,447.4
A137: Бүрэлдэхүүн (Component) | B137: Өмнөх он (Prev, cum.) | C137: Тайлант он (Cur, cum.) | D137: Өөрчлөлт (Change) | E137: Хувь нэмэр (Contribution, pp) | F137: Жилийн өсөлт (YoY)
A138: Улаанбаатар | B138: 99800.02 | C138: 112244.2 | D138: =C138-B138 | E138: 9.053774 | F138: 0.1247
A139: Төвийн бүс | B139: 13794.73 | C139: 15787.48 | D139: =C139-B139 | E139: 1.449827 | F139: 0.1445
A140: Хангайн бүс | B140: 14970.15 | C140: 16544.05 | D140: =C140-B140 | E140: 1.145092 | F140: 0.1051
A141: Зүүн бүс | B141: 3779.99 | C141: 4305.16 | D141: =C141-B141 | E141: 0.382088 | F141: 0.1389
A142: Баруун бүс | B142: 5102.55 | C142: 5445.2 | D142: =C142-B142 | E142: 0.249295 | F142: 0.0672
A143: Нийт (Total — must equal the headline growth) | B143: =SUM(B138:B142) | C143: =SUM(C138:C142) | D143: =C143-B143 | E143: =SUM(E138:E142) | F143: =IFERROR(C143/B143-1,"")
A144: Салбарын өсөлт (Headline growth, YoY) | E144: 12.2801
A146: Цуваа (series for the chart)
A147: Үе (Period) | B147: Өссөн дүн (Cumulative) | C147: Тухайн үе (Single period)
A148: 2018-01 | B148: 5578.91 | C148: 5578.91
A149: 2018-02 | B149: 10394.58 | C149: 4815.67
A150: 2018-03 | B150: 17997.52 | C150: 7602.94
A151: 2018-04 | B151: 25643.95 | C151: 7646.43
A152: 2018-05 | B152: 35374.64 | C152: 9730.69
A153: 2018-06 | B153: 47094.1 | C153: 11719.46
A154: 2018-07 | B154: 60582.81 | C154: 13488.71
A155: 2018-08 | B155: 73822.64 | C155: 13239.83
A156: 2018-09 | B156: 87334.56 | C156: 13511.92
A157: 2018-10 | B157: 99206.95 | C157: 11872.39
A158: 2018-11 | B158: 108426.17 | C158: 9219.22
A159: 2018-12 | B159: 124244.04 | C159: 15817.87
... A249: 2026-06 | B249: 154326.1 | C249: 46364.24
A252: Нийтийн хоолны салбарын орлого — 2026-06
A253: Сараар, өссөн дүнгээр · нийт 1,072,510.2 сая төг · өмнөх оны мөн үе 982,535.2
A254: Бүрэлдэхүүн (Component) | B254: Өмнөх он (Prev, cum.) | C254: Тайлант он (Cur, cum.) | D254: Өөрчлөлт (Change) | E254: Хувь нэмэр (Contribution, pp) | F254: Жилийн өсөлт (YoY)
A255: Улаанбаатар | B255: 799763.34 | C255: 876595.32 | D255: =C255-B255 | E255: 7.819769 | F255: 0.0961
A256: Төвийн бүс | B256: 108442.17 | C256: 114477.26 | D256: =C256-B256 | E256: 0.614237 | F256: 0.0557
A257: Хангайн бүс | B257: 42699.47 | C257: 46846.74 | D257: =C257-B257 | E257: 0.422099 | F257: 0.0971
A258: Зүүн бүс | B258: 20610.13 | C258: 22142.98 | D258: =C258-B258 | E258: 0.15601 | F258: 0.0744
A259: Баруун бүс | B259: 11020.07 | C259: 12447.91 | D259: =C259-B259 | E259: 0.145322 | F259: 0.1296
A260: Нийт (Total — must equal the headline growth) | B260: =SUM(B255:B259) | C260: =SUM(C255:C259) | D260: =C260-B260 | E260: =SUM(E255:E259) | F260: =IFERROR(C260/B260-1,"")
A261: Салбарын өсөлт (Headline growth, YoY) | E261: 9.1574
A263: Цуваа (series for the chart)
A264: Үе (Period) | B264: Өссөн дүн (Cumulative) | C264: Тухайн үе (Single period)
A265: 2018-01 | B265: 34934.4 | C265: 34934.4
A266: 2018-02 | B266: 67821.93 | C266: 32887.53
A267: 2018-03 | B267: 113514.74 | C267: 45692.81
A268: 2018-04 | B268: 156221.67 | C268: 42706.93
A269: 2018-05 | B269: 204613.44 | C269: 48391.77
A270: 2018-06 | B270: 255257.7 | C270: 50644.26
A271: 2018-07 | B271: 306438.28 | C271: 51180.58
A272: 2018-08 | B272: 363321.26 | C272: 56882.98
A273: 2018-09 | B273: 419902.22 | C273: 56580.96
A274: 2018-10 | B274: 481943.73 | C274: 62041.51
A275: 2018-11 | B275: 534160.19 | C275: 52216.46
A276: 2018-12 | B276: 606276.62 | C276: 72116.43
... A366: 2026-06 | B366: 1072510.2 | C366: 214595.66
A369: Барилга угсралт, их засварын ажил — 2026-Q2
A370: Улирлаар, өссөн дүнгээр · нийт 4,795,735.2 сая төг · өмнөх оны мөн үе 5,077,599.1
A371: Бүрэлдэхүүн (Component) | B371: Өмнөх он (Prev, cum.) | C371: Тайлант он (Cur, cum.) | D371: Өөрчлөлт (Change) | E371: Хувь нэмэр (Contribution, pp) | F371: Жилийн өсөлт (YoY)
A372: Орон сууцны барилга | B372: 1892841 | C372: 2007549.4 | D372: =C372-B372 | E372: 2.259108 | F372: 0.0606
A373: Их засварын ажил | B373: 228677.04 | C373: 245237.1 | D373: =C373-B373 | E373: 0.32614 | F373: 0.0724
A374: Инженерийн барилга, байгууламж | B374: 1342476.6 | C374: 1346230.9 | D374: =C374-B374 | E374: 0.07394 | F374: 0.0028
A375: Орон сууцны бус барилга | B375: 1613604.5 | C375: 1059017.4 | D375: =C375-B375 | E375: -10.92223 | F375: -0.3437
A376: Нийт (Total — must equal the headline growth) | B376: =SUM(B372:B375) | C376: =SUM(C372:C375) | D376: =C376-B376 | E376: =SUM(E372:E375) | F376: =IFERROR(C376/B376-1,"")
A377: Салбарын өсөлт (Headline growth, YoY) | E377: -5.5511
A379: Цуваа (series for the chart)
A380: Үе (Period) | B380: Өссөн дүн (Cumulative) | C380: Тухайн үе (Single period)
A381: 1989-Q4 | B381: 2898.9 | C381: 2898.9
A382: 1990-Q4 | B382: 2636.6 | C382: 2636.6
A383: 1991-Q4 | B383: 3010 | C383: 3010
A384: 1992-Q4 | B384: 3074.5 | C384: 3074.5
A385: 1993-Q4 | B385: 15035.4 | C385: 15035.4
A386: 1994-Q4 | B386: 10543.6 | C386: 10543.6
A387: 1995-Q4 | B387: 36889.2 | C387: 36889.2
A388: 1996-Q4 | B388: 63484.2 | C388: 63484.2
A389: 1997-Q4 | B389: 69346.6 | C389: 69346.6
A390: 1998-Q4 | B390: 44797.9 | C390: 44797.9
A391: 1999-Q4 | B391: 78143.1 | C391: 78143.1
...

Sheet Sector_Charts
A1: Эдийн засгийн голлох салбаруудын гүйцэтгэл (Performance of the main economic sectors)
A2: Deck slides 16-21. Each chart stacks the components' contributions with the sector's own growth as a line, in the house style. Values are fractions shown as percentages; the contributions in each row sum to that row's growth. Copy a chart straight into the deck, or read the block beneath it. Each chart shows the last three years — change CHART_WINDOW in excel_builder.py for a longer view.
A4: МЭДЭЭЛЛИЙН ОН САР / DATA AS OF: 2026-06, 2026-07, 2026-Q2 [тайлант үе / reported month: 2026-07]
A6: Худалдааны салбарын нийт борлуулалт — 2026-06
A7: Үе (Period) | B7: Улаанбаатар | C7: Төвийн бүс | D7: Хангайн бүс | E7: Баруун бүс | F7: Зүүн бүс | G7: Салбарын өсөлт (Growth) | H7: Нийлбэр (check)
A8: 2023-07 | B8: 0.231076 | C8: 0.01898 | D8: 0.005965 | E8: 0.003403 | F8: 0.004394 | G8: 0.263818 | H8: =ROUND(SUM(B8:F8)-G8,5)
A9: 2023-08 | B9: 0.229299 | C9: 0.018741 | D9: 0.005779 | E9: 0.003515 | F9: 0.004237 | G9: 0.261571 | H9: =ROUND(SUM(B9:F9)-G9,5)
A10: 2023-09 | B10: 0.210895 | C10: 0.018924 | D10: 0.005726 | E10: 0.0035 | F10: 0.004417 | G10: 0.243462 | H10: =ROUND(SUM(B10:F10)-G10,5)
A11: 2023-10 | B11: 0.206203 | C11: 0.01857 | D11: 0.006006 | E11: 0.003528 | F11: 0.004597 | G11: 0.238904 | H11: =ROUND(SUM(B11:F11)-G11,5)
A12: 2023-11 | B12: 0.203593 | C12: 0.017747 | D12: 0.005932 | E12: 0.003422 | F12: 0.00453 | G12: 0.235223 | H12: =ROUND(SUM(B12:F12)-G12,5)
A13: 2023-12 | B13: 0.202206 | C13: 0.01662 | D13: 0.0062 | E13: 0.003362 | F13: 0.004345 | G13: 0.232734 | H13: =ROUND(SUM(B13:F13)-G13,5)
A14: 2024-01 | B14: 0.207924 | C14: 0.008054 | D14: 0.007297 | E14: 0.00449 | F14: 0.005534 | G14: 0.233298 | H14: =ROUND(SUM(B14:F14)-G14,5)
A15: 2024-02 | B15: 0.184907 | C15: 0.009175 | D15: 0.004521 | E15: 0.003919 | F15: 0.002942 | G15: 0.205465 | H15: =ROUND(SUM(B15:F15)-G15,5)
A16: 2024-03 | B16: 0.172224 | C16: 0.009478 | D16: 0.00138 | E16: 0.003205 | F16: 0.002366 | G16: 0.188653 | H16: =ROUND(SUM(B16:F16)-G16,5)
A17: 2024-04 | B17: 0.18392 | C17: 0.010149 | D17: 0.003375 | E17: 0.003003 | F17: 0.002297 | G17: 0.202744 | H17: =ROUND(SUM(B17:F17)-G17,5)
A18: 2024-05 | B18: 0.176408 | C18: 0.009661 | D18: 0.003495 | E18: 0.002949 | F18: 0.002679 | G18: 0.195192 | H18: =ROUND(SUM(B18:F18)-G18,5)
A19: 2024-06 | B19: 0.144887 | C19: 0.009124 | D19: 0.003486 | E19: 0.003204 | F19: 0.002635 | G19: 0.163336 | H19: =ROUND(SUM(B19:F19)-G19,5)
... A43: 2026-06 | B43: 0.085952 | C43: 0.008731 | D43: 0.003907 | E43: 0.001211 | F43: 0.000875 | G43: 0.100677 | H43: =ROUND(SUM(B43:F43)-G43,5)
A44: Шалгалт: сүүлийн багана бүх мөрөнд 0 байх ёстой (the check column must read 0 on every row — the bars stack up to the line)
A67: Зочид буудлын салбарын орлого — 2026-06
A68: Үе (Period) | B68: Улаанбаатар | C68: Төвийн бүс | D68: Хангайн бүс | E68: Зүүн бүс | F68: Баруун бүс | G68: Салбарын өсөлт (Growth) | H68: Нийлбэр (check)
A69: 2023-07 | B69: 0.320337 | C69: 0.028804 | D69: 0.024767 | E69: 0.005673 | F69: 0.013805 | G69: 0.393385 | H69: =ROUND(SUM(B69:F69)-G69,5)
A70: 2023-08 | B70: 0.340005 | C70: 0.028781 | D70: 0.026404 | E70: 0.006642 | F70: 0.013954 | G70: 0.415787 | H70: =ROUND(SUM(B70:F70)-G70,5)
A71: 2023-09 | B71: 0.323969 | C71: 0.029485 | D71: 0.028849 | E71: 0.007068 | F71: 0.015182 | G71: 0.404553 | H71: =ROUND(SUM(B71:F71)-G71,5)
A72: 2023-10 | B72: 0.312924 | C72: 0.02814 | D72: 0.030023 | E72: 0.007384 | F72: 0.015587 | G72: 0.394058 | H72: =ROUND(SUM(B72:F72)-G72,5)
A73: 2023-11 | B73: 0.304151 | C73: 0.024855 | D73: 0.034805 | E73: 0.007861 | F73: 0.016362 | G73: 0.388034 | H73: =ROUND(SUM(B73:F73)-G73,5)
A74: 2023-12 | B74: 0.293444 | C74: 0.020907 | D74: 0.037151 | E74: 0.003458 | F74: 0.016585 | G74: 0.371544 | H74: =ROUND(SUM(B74:F74)-G74,5)
A75: 2024-01 | B75: 0.04512 | C75: 0.003526 | D75: 0.043991 | E75: 0.000917 | F75: 0.000631 | G75: 0.094183 | H75: =ROUND(SUM(B75:F75)-G75,5)
A76: 2024-02 | B76: 0.054939 | C76: 0.003634 | D76: 0.052242 | E76: 0.00022 | F76: -0.001205 | G76: 0.109831 | H76: =ROUND(SUM(B76:F76)-G76,5)
A77: 2024-03 | B77: 0.04241 | C77: -0.000487 | D77: 0.045821 | E77: -0.001012 | F77: 0.003382 | G77: 0.090113 | H77: =ROUND(SUM(B77:F77)-G77,5)
A78: 2024-04 | B78: 0.07709 | C78: 0.005198 | D78: 0.048713 | E78: -0.000387 | F78: 0.00654 | G78: 0.137154 | H78: =ROUND(SUM(B78:F78)-G78,5)
A79: 2024-05 | B79: 0.07732 | C79: 0.007243 | D79: 0.047614 | E79: 0.001232 | F79: 0.006939 | G79: 0.140349 | H79: =ROUND(SUM(B79:F79)-G79,5)
A80: 2024-06 | B80: 0.062529 | C80: 0.005975 | D80: 0.044291 | E80: 0.001333 | F80: 0.007028 | G80: 0.121156 | H80: =ROUND(SUM(B80:F80)-G80,5)
... A104: 2026-06 | B104: 0.090538 | C104: 0.014498 | D104: 0.011451 | E104: 0.003821 | F104: 0.002493 | G104: 0.122801 | H104: =ROUND(SUM(B104:F104)-G104,5)
A105: Шалгалт: сүүлийн багана бүх мөрөнд 0 байх ёстой (the check column must read 0 on every row — the bars stack up to the line)
A106: Үе (Period) | B106: Тухайн үе (сая төг) | C106: Өссөн дүнгийн жилийн өсөлт
A107: 2023-07 | B107: 27214.93 | C107: 0.393385
A108: 2023-08 | B108: 28549.63 | C108: 0.415787
A109: 2023-09 | B109: 25607.6 | C109: 0.404553
A110: 2023-10 | B110: 22275.12 | C110: 0.394058
A111: 2023-11 | B111: 20912.8 | C111: 0.388034
A112: 2023-12 | B112: 30553.34 | C112: 0.371544
A113: 2024-01 | B113: 15545.88 | C113: 0.094183
A114: 2024-02 | B114: 12892.6 | C114: 0.109831
A115: 2024-03 | B115: 18016.4 | C115: 0.090113
A116: 2024-04 | B116: 20223.82 | C116: 0.137154
A117: 2024-05 | B117: 23401.24 | C117: 0.140349
A118: 2024-06 | B118: 30052.29 | C118: 0.121156
... A142: 2026-06 | B142: 46364.24 | C142: 0.122801
A165: Нийтийн хоолны салбарын орлого — 2026-06
A166: Үе (Period) | B166: Улаанбаатар | C166: Төвийн бүс | D166: Хангайн бүс | E166: Зүүн бүс | F166: Баруун бүс | G166: Салбарын өсөлт (Growth) | H166: Нийлбэр (check)
A167: 2023-07 | B167: 0.210961 | C167: 0.013515 | D167: 0.006215 | E167: 0.002805 | F167: 0.000724 | G167: 0.234219 | H167: =ROUND(SUM(B167:F167)-G167,5)
A168: 2023-08 | B168: 0.214284 | C168: 0.013127 | D168: 0.006392 | E168: 0.003018 | F168: 0.001084 | G168: 0.237904 | H168: =ROUND(SUM(B168:F168)-G168,5)
A169: 2023-09 | B169: 0.212283 | C169: 0.011011 | D169: 0.007299 | E169: 0.003332 | F169: 0.001152 | G169: 0.235076 | H169: =ROUND(SUM(B169:F169)-G169,5)
A170: 2023-10 | B170: 0.208163 | C170: 0.010611 | D170: 0.007707 | E170: 0.003603 | F170: 0.001161 | G170: 0.231245 | H170: =ROUND(SUM(B170:F170)-G170,5)
A171: 2023-11 | B171: 0.204691 | C171: 0.011267 | D171: 0.007957 | E171: 0.003784 | F171: 0.00101 | G171: 0.228709 | H171: =ROUND(SUM(B171:F171)-G171,5)
A172: 2023-12 | B172: 0.205684 | C172: 0.011384 | D172: 0.008337 | E172: 0.003622 | F172: 0.001069 | G172: 0.230095 | H172: =ROUND(SUM(B172:F172)-G172,5)
A173: 2024-01 | B173: 0.179065 | C173: 0.01333 | D173: 0.007965 | E173: 0.004166 | F173: 0.003329 | G173: 0.207856 | H173: =ROUND(SUM(B173:F173)-G173,5)
A174: 2024-02 | B174: 0.204676 | C174: 0.016388 | D174: 0.00851 | E174: 0.00281 | F174: 0.003538 | G174: 0.235921 | H174: =ROUND(SUM(B174:F174)-G174,5)
A175: 2024-03 | B175: 0.17018 | C175: 0.017885 | D175: 0.008297 | E175: 0.00252 | F175: 0.003329 | G175: 0.202212 | H175: =ROUND(SUM(B175:F175)-G175,5)
A176: 2024-04 | B176: 0.176919 | C176: 0.017307 | D176: 0.009257 | E176: 0.003264 | F176: 0.003972 | G176: 0.210719 | H176: =ROUND(SUM(B176:F176)-G176,5)
A177: 2024-05 | B177: 0.174925 | C177: 0.016493 | D177: 0.009755 | E177: 0.00402 | F177: 0.00425 | G177: 0.209444 | H177: =ROUND(SUM(B177:F177)-G177,5)
A178: 2024-06 | B178: 0.164353 | C178: 0.014244 | D178: 0.010578 | E178: 0.004174 | F178: 0.00459 | G178: 0.19794 | H178: =ROUND(SUM(B178:F178)-G178,5)
... A202: 2026-06 | B202: 0.078198 | C202: 0.006142 | D202: 0.004221 | E202: 0.00156 | F202: 0.001453 | G202: 0.091574 | H202: =ROUND(SUM(B202:F202)-G202,5)
A203: Шалгалт: сүүлийн багана бүх мөрөнд 0 байх ёстой (the check column must read 0 on every row — the bars stack up to the line)
A204: Үе (Period) | B204: Тухайн үе (сая төг) | C204: Өссөн дүнгийн жилийн өсөлт
A205: 2023-07 | B205: 136366.06 | C205: 0.234219
A206: 2023-08 | B206: 153585.54 | C206: 0.237904
A207: 2023-09 | B207: 146858.7 | C207: 0.235076
A208: 2023-10 | B208: 150613.48 | C208: 0.231245
A209: 2023-11 | B209: 143138.43 | C209: 0.228709
A210: 2023-12 | B210: 190314.94 | C210: 0.230095
A211: 2024-01 | B211: 122275.47 | C211: 0.207856
A212: 2024-02 | B212: 114507.32 | C212: 0.235921
A213: 2024-03 | B213: 148798.31 | C213: 0.202212
A214: 2024-04 | B214: 159673.46 | C214: 0.210719
A215: 2024-05 | B215: 169596.42 | C215: 0.209444
A216: 2024-06 | B216: 173679.59 | C216: 0.19794
... A240: 2026-06 | B240: 214595.66 | C240: 0.091574
A263: Барилга угсралт, их засварын ажил — 2026-Q2
A264: Үе (Period) | B264: Орон сууцны барилга | C264: Их засварын ажил | D264: Инженерийн барилга, байгууламж | E264: Орон сууцны бус барилга | F264: Салбарын өсөлт (Growth) | G264: Нийлбэр (check)
A265: 2022-Q2 | B265: 0.164805 | C265: 0.011175 | D265: 0.114697 | E265: 0.022975 | F265: 0.313651 | G265: =ROUND(SUM(B265:E265)-F265,5)
A266: 2022-Q3 | B266: 0.135848 | C266: 0.015638 | D266: 0.086227 | E266: 0.030316 | F266: 0.268029 | G266: =ROUND(SUM(B266:E266)-F266,5)
A267: 2022-Q4 | B267: 0.154693 | C267: 0.013919 | D267: 0.103881 | E267: 0.055899 | F267: 0.328393 | G267: =ROUND(SUM(B267:E267)-F267,5)
A268: 2023-Q1 | B268: 0.25388 | C268: 0.0031 | D268: -0.152659 | E268: 0.189529 | F268: 0.29385 | G268: =ROUND(SUM(B268:E268)-F268,5)
A269: 2023-Q2 | B269: 0.113874 | C269: 0.011651 | D269: -0.068422 | E269: 0.147812 | F269: 0.204914 | G269: =ROUND(SUM(B269:E269)-F269,5)
A270: 2023-Q3 | B270: 0.102545 | C270: 0.014876 | D270: -0.02081 | E270: 0.119006 | F270: 0.215617 | G270: =ROUND(SUM(B270:E270)-F270,5)
A271: 2023-Q4 | B271: 0.087706 | C271: 0.01363 | D271: -0.032203 | E271: 0.111255 | F271: 0.180388 | G271: =ROUND(SUM(B271:E271)-F271,5)
A272: 2024-Q1 | B272: 0.048741 | C272: 0.000749 | D272: 0.165292 | E272: 0.115006 | F272: 0.329789 | G272: =ROUND(SUM(B272:E272)-F272,5)
A273: 2024-Q2 | B273: 0.030808 | C273: -0.00206 | D273: 0.181701 | E273: 0.030342 | F273: 0.240791 | G273: =ROUND(SUM(B273:E273)-F273,5)
A274: 2024-Q3 | B274: 0.028281 | C274: -0.002477 | D274: 0.082736 | E274: 0.02218 | F274: 0.130721 | G274: =ROUND(SUM(B274:E274)-F274,5)
A275: 2024-Q4 | B275: 0.020225 | C275: 0.004297 | D275: 0.095857 | E275: 0.026468 | F275: 0.146847 | G275: =ROUND(SUM(B275:E275)-F275,5)
A276: 2025-Q1 | B276: 0.075832 | C276: 0.011896 | D276: -0.052615 | E276: -0.012752 | F276: 0.022362 | G276: =ROUND(SUM(B276:E276)-F276,5)
... A280: 2026-Q1 | B280: 0.2935 | C280: 0.015596 | D280: 0.048098 | E280: -0.073321 | F280: 0.283873 | G280: =ROUND(SUM(B280:E280)-F280,5)
A281: Шалгалт: сүүлийн багана бүх мөрөнд 0 байх ёстой (the check column must read 0 on every row — the bars stack up to the line)
A304: Аж үйлдвэрийн салбарын бүтээгдэхүүний борлуулалт — 2026-07
A305: Үе (Period) | B305: Уул уурхай, олборлолт | C305: Боловсруулах үйлдвэрлэл | D305: Цахилгаан хий, уур, агааржуулалт | E305: Ус хангамж; бохир ус зайлуулах систем, хог, хаягдлын менежмент болон цэвэрлэх үйл ажиллагаа | F305: Салбарын өсөлт (Growth) | G305: Нийлбэр (check)
A306: 2023-08 | B306: 0.622887 | C306: 0.081228 | D306: 0.015344 | E306: 0.00125 | F306: 0.720709 | G306: =ROUND(SUM(B306:E306)-F306,5)
A307: 2023-09 | B307: 0.569937 | C307: 0.076128 | D307: 0.014508 | E307: 0.001181 | F307: 0.661754 | G307: =ROUND(SUM(B307:E307)-F307,5)
A308: 2023-10 | B308: 0.550451 | C308: 0.071721 | D308: 0.013648 | E308: 0.001167 | F308: 0.636988 | G308: =ROUND(SUM(B308:E308)-F308,5)
...

Sheet Weekly_Prices
A1: 7 хоногийн үнийн мэдээ, Улаанбаатар (Weekly prices, Ulaanbaatar)
A2: Deck slide 9. Source: NSO, Хүнсний гол нэрийн барааны 7 хоногийн үнийн мэдээ. Prices in tugrik. YTD compares the latest week with the first week of the reported year; YoY with the same week last year.
A4: МЭДЭЭЛЛИЙН ОН САР / DATA AS OF: 2026-08-17 (7 хоног бүр / weekly) [тайлант үе / reported month: 2026-07] ← ТЭРГҮҮЛЭХ ҮЗҮҮЛЭЛТ: тайлант сараас хойшхи 7 хоногийг хассангүй. Тайлант сарын сүүлийн 7 хоног: 2026-07-27 (leading indicator — weeks after the reported month are kept; last week inside it was 2026-07-27)
A5: Эх файл (source table): nso_weekly_prices.json · capital city (DT_NSO_0600_001V4) -> 2026-08-17 (285 weeks) · by aimag (DT_NSO_0300_010V5) -> 2026-08-17 (132 weeks)
A7: Бүлгээр (by group — simple average of the members' changes)
A8: Бүлэг (Group) | B8: Оны эхнээс (YTD) | C8: Жилийн өмнөхөөс (YoY) | D8: Бүрэлдэхүүн
A9: Мах (meat) | B9: 0.4001 | C9: 0.5211 | D9: Хонины мах, ястай, кг, Үхрийн мах, ястай, кг, Үхрийн мах, цул, кг, Адууны мах, ястай, кг, Ямааны мах, ястай, кг
A10: Шатахуун (fuel) | B10: 0.1393 | C10: 0.1951 | D10: Аи-80 автобензин, л, Аи-92 автобензин, л, Дизелийн түлш, л, Аи-92, Евро, автобензин, л
A11: Гурил, талх (flour, bread) | B11: 0.0596 | C11: 0.1036 | D11: Гурил, дээд зэрэг, савласан, 1 кг, Гурил, I зэрэг, савласан, кг, Гурил, 2-р зэрэг, савласан, кг, Талх, 600 гр, Талх, зүссэн, 600 гр, Хар талх, 300 гр, Цагаан будаа, кг
A12: Бусад хүнс (other food) | B12: 0.0446 | C12: 0.0536 | D12: Сүү, задгай, л, Сүү, ууттай, 0.5 л, Сүү, савтай, л, Тараг, савласан, 900 гр, Цөцгийн тос, 200 гр, Ургамлын тос, л, Элсэн чихэр, кг, Ногоон цай, савласан, 90 г, Өндөг, ш, Алим, кг, Төмс, кг, Лууван, кг, Байцаа, кг, Хүрэн манжин, кг
A14: Бүтээгдэхүүнээр (by product)
A15: Бүтээгдэхүүн (Product) | B15: Сүүлийн үнэ (Latest, 2026-08-17) | C15: Тайлант сарын эцэст (2026-07-27) | D15: Оны эхнээс (YTD) | E15: Жилийн өмнөхөөс (YoY)
A16: Гурил, дээд зэрэг, савласан, 1 кг | B16: 3512 | C16: 3512 | D16: 0.0014 | E16: 0.0763
A17: Гурил, I зэрэг, савласан, кг | B17: 2521 | C17: 2521 | D17: 0.0052 | E17: 0.0539
A18: Гурил, 2-р зэрэг, савласан, кг | B18: 1467 | C18: 1467 | D18: 0.0471 | E18: 0.0989
A19: Талх, 600 гр | B19: 2926 | C19: 2926 | D19: 0.0809 | E19: 0.1376
A20: Талх, зүссэн, 600 гр | B20: 3926 | C20: 3899 | D20: 0.1868 | E20: 0.2032
A21: Хар талх, 300 гр | B21: 2779 | C21: 2769 | D21: 0.0889 | E21: 0.1129
A22: Цагаан будаа, кг | B22: 5000 | C22: 5000 | D22: 0.0068 | E22: 0.0421
A23: Хонины мах, ястай, кг | B23: 26152 | C23: 27417 | D23: 0.5079 | E23: 0.543
A24: Үхрийн мах, ястай, кг | B24: 31680 | C24: 32470 | D24: 0.3965 | E24: 0.5038
A25: Үхрийн мах, цул, кг | B25: 36611 | C25: 37878 | D25: 0.397 | E25: 0.5043
A26: Адууны мах, ястай, кг | B26: 18440 | C26: 18327 | D26: 0.2473 | E26: 0.4041
A27: Ямааны мах, ястай, кг | B27: 20328 | C27: 20646 | D27: 0.452 | E27: 0.6504
... A45: Дизелийн түлш, л | B45: 4185 | C45: 4185 | D45: 0.3328 | E45: 0.4115
A46: Аи-92, Евро, автобензин, л | B46: 3121 | C46: 3121 | D46: 0.0508
A49: Долоо хоногийн цуваа — махны болон шатахууны үнэ (weekly series, meat and fuel)
A50: 7 хоног (Week) | B50: Хонины мах, ястай, кг | C50: Үхрийн мах, ястай, кг | D50: Үхрийн мах, цул, кг | E50: Аи-80 автобензин, л | F50: Аи-92 автобензин, л | G50: Дизелийн түлш, л | H50: Аи-92, Евро, автобензин, л
A51: 2024-01-15 | B51: 12845 | C51: 16309 | D51: 18660 | E51: 2345 | F51: 2390 | G51: 3890
A52: 2024-01-22 | B52: 13180 | C52: 16465 | D52: 18679 | E52: 2345 | F52: 2390 | G52: 3890
A53: 2024-01-29 | B53: 13259 | C53: 16768 | D53: 18836 | E53: 2345 | F53: 2390 | G53: 3890
A54: 2024-02-05 | B54: 13788 | C54: 17091 | D54: 19225 | E54: 2345 | F54: 2390 | G54: 3890
A55: 2024-02-19 | B55: 13688 | C55: 17105 | D55: 19224 | E55: 2345 | F55: 2390 | G55: 3590
A56: 2024-02-26 | B56: 13852 | C56: 17254 | D56: 19170 | E56: 2345 | F56: 2390 | G56: 3590
A57: 2024-03-04 | B57: 13966 | C57: 17445 | D57: 19528 | E57: 2345 | F57: 2390 | G57: 3590
A58: 2024-03-11 | B58: 13933 | C58: 17655 | D58: 19642 | E58: 2345 | F58: 2390 | G58: 3590
A59: 2024-03-18 | B59: 13902 | C59: 17565 | D59: 19743 | E59: 2345 | F59: 2390 | G59: 3590
A60: 2024-03-25 | B60: 13867 | C60: 17831 | D60: 19780 | E60: 2345 | F60: 2390 | G60: 3590
A61: 2024-04-01 | B61: 14257 | C61: 17897 | D61: 19753 | E61: 2345 | F61: 2390 | G61: 3590
A62: 2024-04-08 | B62: 14385 | C62: 18036 | D62: 19881 | E62: 2345 | F62: 2390 | G62: 3590
... A161: 2026-03-30 | B161: 21984 | C161: 26976 | D161: 30887 | E161: 2345 | F161: 2590 | G161: 3447
A162: 2026-04-06 | B162: 23724 | C162: 28328 | D162: 31819 | F162: 2590 | G162: 3987 | H162: 2970
A163: 2026-04-13 | B163: 24984 | C163: 28545 | D163: 32733 | F163: 2590 | G163: 4335 | H163: 2970
A164: 2026-04-20 | B164: 25483 | C164: 28913 | D164: 33802 | F164: 2590 | G164: 4335 | H164: 2970
A165: 2026-04-27 | B165: 25729 | C165: 29880 | D165: 34707 | F165: 2590 | G165: 4335 | H165: 2970
A166: 2026-05-04 | B166: 26337 | C166: 30521 | D166: 35436 | F166: 2590 | G166: 4335 | H166: 2926
A167: 2026-05-11 | B167: 26506 | C167: 30820 | D167: 35848 | F167: 2590 | G167: 4335 | H167: 2780
A168: 2026-05-18 | B168: 26740 | C168: 31474 | D168: 36669 | F168: 2590 | G168: 4335 | H168: 2780
A169: 2026-05-25 | B169: 26651 | C169: 32329 | D169: 37101 | F169: 2590 | G169: 4335 | H169: 2780
A170: 2026-06-02 | B170: 27666 | C170: 33742 | D170: 37835 | F170: 2590 | G170: 4335 | H170: 2780
A171: 2026-06-08 | B171: 27763 | C171: 33883 | D171: 38210 | F171: 2590 | G171: 4335 | H171: 2967
A172: 2026-06-15 | B172: 27413 | C172: 33883 | D172: 38125 | F172: 2590 | G172: 4335 | H172: 2960
A173: 2026-06-22 | B173: 27850 | C173: 34222 | D173: 38619 | F173: 2590 | G173: 4335 | H173: 2960
... A180: 2026-08-17 | B180: 26152 | C180: 31680 | D180: 36611 | F180: 3040 | G180: 4185 | H180: 3121

Sheet Forecast
A1: IMF World Economic Outlook — төсөөлөл (projections)
A2: ТӨСӨӨЛӨЛ, ХЭМЖИЛТ БИШ / PROJECTIONS, NOT MEASUREMENTS. Annual figures from the IMF's twice-yearly World Economic Outlook. Every other sheet in this workbook measures what happened; this one states what the IMF expects. Never present a figure from this sheet as an outturn.
A4: No IMF WEO export cached — drop the CSV from imf.org into raw_data/ (any name containing 'WEO').

Sheet Budget
A1: State budget
A2: Deck slide 13. Source: Mongolbank statistical bulletin. Coal actual links to the Commodities sheet.
A4: МЭДЭЭЛЛИЙН ОН САР / DATA AS OF: Mongolbank bulletin — 2026-07 (CURRENT) [тайлант үе / reported month: 2026-07]
A6: Үзүүлэлт (Indicator) | B6: Утга (Value) | C6: Нэгж (Unit) | D6: Note
A7: Төсвийн тэнцэл (Budget balance, cumulative) | B7: -2206.4 | C7: bln MNT | D7: Mongolbank bulletin (mongolbank_bulletin.xlsx)
A8: Төсвийн орлого, гүйцэтгэл (Revenue collected, cumulative) | B8: 19829.8 | C8: bln MNT | D8: Mongolbank bulletin (mongolbank_bulletin.xlsx)
A9: Төсвийн зарлага, гүйцэтгэл (Expenditure, cumulative) | B9: 19507.2 | C9: bln MNT | D9: Mongolbank bulletin (mongolbank_bulletin.xlsx)
A10: Төсвийн орлого, төлөвлөгөө (Revenue plan, annual) | C10: tln MNT | D10: MANUAL: annual plan figure, set once a year
A11: Нүүрсний экспортын төлөвлөгөө (Coal export plan, annual) | C11: mln t | D11: MANUAL: annual plan figure, set once a year
A12: Нүүрсний экспорт, гүйцэтгэл (Coal export actual) | B12: =IFERROR(Commodities!D7/1E9,"") | C12: mln t | D12: 2026 оны 7-р сарын байдлаар

Sheet Coverage
A1: Deck coverage — what this workbook automates
A2: AUTO = filled by pipeline | MISSING = source not yet wired (see note) | MANUAL = can never be data-driven.
A4: МЭДЭЭЛЛИЙН ОН САР / DATA AS OF: энэ хуудас бүтэц, тоо биш (this sheet is structure, not data). [тайлант үе / reported month: 2026-07]
A6: Slide | B6: Content | C6: Status | D6: Source | E6: Note
A7: 1 | B7: Title / date | C7: AUTO | D7: pipeline | E7: report_period string
A8: 2 | B8: Geopolitics | C8: MANUAL | D8: - | E8: editorial; no data feed
A9: 3 | B9: Macro forecast snapshot | C9: AUTO | D9: Bulletin+NSO+MB | E9: policy rate auto
A10: 4 | B10: Real GDP cumulative growth | C10: AUTO | D10: NSO
A11: 5 | B11: Sector contributions | C11: AUTO | D11: NSO | E11: NSO table has 10 aggregated sectors
A12: 6 | B12: Inflation vs target | C12: AUTO | D12: MB bulletin | E12: headline + 16-month national/UB CPI series, all auto
A13: 7 | B13: Meat & fuel prices | C13: MANUAL | D13: NSO CPI PDF | E13: by decision (2026-07): heavy PDF parsing not worth automating; enter values by hand
A14: 8 | B14: Inflation -> interest rates | C14: AUTO | D14: MB bulletin | E14: policy & deposit rate monthly series + CPI, all auto
A15: 9 | B15: Trade balance & commodities | C15: AUTO | D15: Customs
A16: 10 | B16: Export volumes | C16: AUTO | D16: Customs
A17: 11 | B17: Border prices | C17: AUTO | D17: Customs | E17: monthly marginal unit values
A18: 12 | B18: Balance of payments | C18: AUTO | D18: Mongolbank | E18: CA/KA/FA parsed from bop_manual.xlsx
A19: 13 | B19: State budget | C19: AUTO | D19: MB bulletin
A20: 14 | B20: Household income/expense | C20: MISSING | D20: NSO | E20: needs Household Socio-Economic Survey table id
A21: 15 | B21: Household debt | C21: MISSING | D21: NSO | E21: same survey table
A22: 16 | B22: Banking sector | C22: AUTO | D22: Mongolbank | E22: balance-sheet xlsx parsed: assets, loans, CB securities, deposits, past-due, NPL, equity + monthly series
A23: 17 | B23: Moody's slides (17-22) | C23: MANUAL | D23: Moody's | E23: proprietary images; never automatable
